[
  {
    "id": "Hv9CS6KZayQ",
    "created_at": "2022-08-31T14:36:55Z",
    "updated_at": "2023-01-11T18:34:07Z",
    "promoted_at": null,
    "width": 8256,
    "height": 5504,
    "color": "#c0c0c0",
    "blur_hash": "LFJ89A_N9K?cbVxbx^t6DQ-pWRt7",
    "description": null,
    "alt_description": null,
    "urls": {
      "raw": "https://images.unsplash.com/photo-1661956602944-249bcd04b63f?ixid=MnwzODY1NDR8MXwxfGFsbHwxfHx8fHx8Mnx8MTY3MzUyMjY2Mg&ixlib=rb-4.0.3",
      "full": "https://images.unsplash.com/photo-1661956602944-249bcd04b63f?crop=entropy&cs=tinysrgb&fm=jpg&ixid=MnwzODY1NDR8MXwxfGFsbHwxfHx8fHx8Mnx8MTY3MzUyMjY2Mg&ixlib=rb-4.0.3&q=80",
      "regular": "https://images.unsplash.com/photo-1661956602944-249bcd04b63f?crop=entropy&cs=tinysrgb&fit=max&fm=jpg&ixid=MnwzODY1NDR8MXwxfGFsbHwxfHx8fHx8Mnx8MTY3MzUyMjY2Mg&ixlib=rb-4.0.3&q=80&w=1080",
      "small": "https://images.unsplash.com/photo-1661956602944-249bcd04b63f?crop=entropy&cs=tinysrgb&fit=max&fm=jpg&ixid=MnwzODY1NDR8MXwxfGFsbHwxfHx8fHx8Mnx8MTY3MzUyMjY2Mg&ixlib=rb-4.0.3&q=80&w=400",
      "thumb": "https://images.unsplash.com/photo-1661956602944-249bcd04b63f?crop=entropy&cs=tinysrgb&fit=max&fm=jpg&ixid=MnwzODY1NDR8MXwxfGFsbHwxfHx8fHx8Mnx8MTY3MzUyMjY2Mg&ixlib=rb-4.0.3&q=80&w=200",
      "small_s3": "https://s3.us-west-2.amazonaws.com/images.unsplash.com/small/photo-1661956602944-249bcd04b63f"
    },
    "links": {
      "self": "https://api.unsplash.com/photos/Hv9CS6KZayQ",
      "html": "https://unsplash.com/photos/Hv9CS6KZayQ",
      "download": "https://unsplash.com/photos/Hv9CS6KZayQ/download?ixid=MnwzODY1NDR8MXwxfGFsbHwxfHx8fHx8Mnx8MTY3MzUyMjY2Mg",
      "download_location": "https://api.unsplash.com/photos/Hv9CS6KZayQ/download?ixid=MnwzODY1NDR8MXwxfGFsbHwxfHx8fHx8Mnx8MTY3MzUyMjY2Mg"
    },
    "likes": 227,
    "liked_by_user": false,
    "current_user_collections": [],
    "sponsorship": {
      "impression_urls": [
        "https://secure.insightexpressai.com/adServer/adServerESI.aspx?script=false&bannerID=10622765&rnd=[timestamp]&redir=https://secure.insightexpressai.com/adserver/1pixel.gif",
        "https://ad.doubleclick.net/ddm/trackimp/N1224323.3286893UNSPLASH/B28192607.344928628;dc_trk_aid=536378214;dc_trk_cid=177019559;ord=[timestamp];dc_lat=;dc_rdid=;tag_for_child_directed_treatment=;tfua=;ltd=?",
        "https://pixel.adsafeprotected.com/rfw/st/1106181/65490056/skeleton.gif?gdpr=${GDPR}&gdpr_consent=${GDPR_CONSENT_278}&gdpr_pd=${GDPR_PD}"
      ],
      "tagline": "Reach the right shoppers and increase orders",
      "tagline_url": "https://ad.doubleclick.net/ddm/trackclk/N1224323.3286893UNSPLASH/B28192607.344928628;dc_trk_aid=536378214;dc_trk_cid=177019559;dc_lat=;dc_rdid=;tag_for_child_directed_treatment=;tfua=;ltd=",
      "sponsor": {
        "id": "D-bxv1Imc-o",
        "updated_at": "2023-01-12T04:08:38Z",
        "username": "mailchimp",
        "name": "Mailchimp",
        "first_name": "Mailchimp",
        "last_name": null,
        "twitter_username": "Mailchimp",
        "portfolio_url": "https://mailchimp.com/",
        "bio": "The all-in-one Marketing Platform built for growing businesses.",
        "location": null,
        "links": {
          "self": "https://api.unsplash.com/users/mailchimp",
          "html": "https://unsplash.com/@mailchimp",
          "photos": "https://api.unsplash.com/users/mailchimp/photos",
          "likes": "https://api.unsplash.com/users/mailchimp/likes",
          "portfolio": "https://api.unsplash.com/users/mailchimp/portfolio",
          "following": "https://api.unsplash.com/users/mailchimp/following",
          "followers": "https://api.unsplash.com/users/mailchimp/followers"
        },
        "profile_image": {
          "small": "https://images.unsplash.com/profile-1609545740442-928866556c38image?ixlib=rb-4.0.3&crop=faces&fit=crop&w=32&h=32",
          "medium": "https://images.unsplash.com/profile-1609545740442-928866556c38image?ixlib=rb-4.0.3&crop=faces&fit=crop&w=64&h=64",
          "large": "https://images.unsplash.com/profile-1609545740442-928866556c38image?ixlib=rb-4.0.3&crop=faces&fit=crop&w=128&h=128"
        },
        "instagram_username": "mailchimp",
        "total_collections": 0,
        "total_likes": 19,
        "total_photos": 13,
        "accepted_tos": true,
        "for_hire": false,
        "social": {
          "instagram_username": "mailchimp",
          "portfolio_url": "https://mailchimp.com/",
          "twitter_username": "Mailchimp",
          "paypal_email": null
        }
      }
    },
    "topic_submissions": {},
    "user": {
      "id": "D-bxv1Imc-o",
      "updated_at": "2023-01-12T04:08:38Z",
      "username": "mailchimp",
      "name": "Mailchimp",
      "first_name": "Mailchimp",
      "last_name": null,
      "twitter_username": "Mailchimp",
      "portfolio_url": "https://mailchimp.com/",
      "bio": "The all-in-one Marketing Platform built for growing businesses.",
      "location": null,
      "links": {
        "self": "https://api.unsplash.com/users/mailchimp",
        "html": "https://unsplash.com/@mailchimp",
        "photos": "https://api.unsplash.com/users/mailchimp/photos",
        "likes": "https://api.unsplash.com/users/mailchimp/likes",
        "portfolio": "https://api.unsplash.com/users/mailchimp/portfolio",
        "following": "https://api.unsplash.com/users/mailchimp/following",
        "followers": "https://api.unsplash.com/users/mailchimp/followers"
      },
      "profile_image": {
        "small": "https://images.unsplash.com/profile-1609545740442-928866556c38image?ixlib=rb-4.0.3&crop=faces&fit=crop&w=32&h=32",
        "medium": "https://images.unsplash.com/profile-1609545740442-928866556c38image?ixlib=rb-4.0.3&crop=faces&fit=crop&w=64&h=64",
        "large": "https://images.unsplash.com/profile-1609545740442-928866556c38image?ixlib=rb-4.0.3&crop=faces&fit=crop&w=128&h=128"
      },
      "instagram_username": "mailchimp",
      "total_collections": 0,
      "total_likes": 19,
      "total_photos": 13,
      "accepted_tos": true,
      "for_hire": false,
      "social": {
        "instagram_username": "mailchimp",
        "portfolio_url": "https://mailchimp.com/",
        "twitter_username": "Mailchimp",
        "paypal_email": null
      }
    }
  },
  {
    "id": "zPwbWPLmKeE",
    "created_at": "2023-01-05T16:57:14Z",
    "updated_at": "2023-01-12T10:44:25Z",
    "promoted_at": "2023-01-12T10:44:25Z",
    "width": 3164,
    "height": 4740,
    "color": "#d9d9d9",
    "blur_hash": "LTOz9;?cw[Rm.AWYWYj[V|acS5t5",
    "description": "Sunrise Coffee Mug",
    "alt_description": "a blue coffee mug sitting on top of a wooden chair",
    "urls": {
      "raw": "https://images.unsplash.com/photo-1672935138600-c9779eda5227?ixid=MnwzODY1NDR8MHwxfGFsbHwyfHx8fHx8Mnx8MTY3MzUyMjY2Mg&ixlib=rb-4.0.3",
      "full": "https://images.unsplash.com/photo-1672935138600-c9779eda5227?crop=entropy&cs=tinysrgb&fm=jpg&ixid=MnwzODY1NDR8MHwxfGFsbHwyfHx8fHx8Mnx8MTY3MzUyMjY2Mg&ixlib=rb-4.0.3&q=80",
      "regular": "https://images.unsplash.com/photo-1672935138600-c9779eda5227?crop=entropy&cs=tinysrgb&fit=max&fm=jpg&ixid=MnwzODY1NDR8MHwxfGFsbHwyfHx8fHx8Mnx8MTY3MzUyMjY2Mg&ixlib=rb-4.0.3&q=80&w=1080",
      "small": "https://images.unsplash.com/photo-1672935138600-c9779eda5227?crop=entropy&cs=tinysrgb&fit=max&fm=jpg&ixid=MnwzODY1NDR8MHwxfGFsbHwyfHx8fHx8Mnx8MTY3MzUyMjY2Mg&ixlib=rb-4.0.3&q=80&w=400",
      "thumb": "https://images.unsplash.com/photo-1672935138600-c9779eda5227?crop=entropy&cs=tinysrgb&fit=max&fm=jpg&ixid=MnwzODY1NDR8MHwxfGFsbHwyfHx8fHx8Mnx8MTY3MzUyMjY2Mg&ixlib=rb-4.0.3&q=80&w=200",
      "small_s3": "https://s3.us-west-2.amazonaws.com/images.unsplash.com/small/photo-1672935138600-c9779eda5227"
    },
    "links": {
      "self": "https://api.unsplash.com/photos/zPwbWPLmKeE",
      "html": "https://unsplash.com/photos/zPwbWPLmKeE",
      "download": "https://unsplash.com/photos/zPwbWPLmKeE/download?ixid=MnwzODY1NDR8MHwxfGFsbHwyfHx8fHx8Mnx8MTY3MzUyMjY2Mg",
      "download_location": "https://api.unsplash.com/photos/zPwbWPLmKeE/download?ixid=MnwzODY1NDR8MHwxfGFsbHwyfHx8fHx8Mnx8MTY3MzUyMjY2Mg"
    },
    "likes": 5,
    "liked_by_user": false,
    "current_user_collections": [],
    "sponsorship": null,
    "topic_submissions": {},
    "user": {
      "id": "VX5zAdFM044",
      "updated_at": "2023-01-12T10:44:25Z",
      "username": "haileymoeller",
      "name": "Hailey Moeller",
      "first_name": "Hailey",
      "last_name": "Moeller",
      "twitter_username": null,
      "portfolio_url": "http://haileylynndesigns.com",
      "bio": null,
      "location": "Ohio",
      "links": {
        "self": "https://api.unsplash.com/users/haileymoeller",
        "html": "https://unsplash.com/@haileymoeller",
        "photos": "https://api.unsplash.com/users/haileymoeller/photos",
        "likes": "https://api.unsplash.com/users/haileymoeller/likes",
        "portfolio": "https://api.unsplash.com/users/haileymoeller/portfolio",
        "following": "https://api.unsplash.com/users/haileymoeller/following",
        "followers": "https://api.unsplash.com/users/haileymoeller/followers"
      },
      "profile_image": {
        "small": "https://images.unsplash.com/profile-1672937944835-e59d56977ec4image?ixlib=rb-4.0.3&crop=faces&fit=crop&w=32&h=32",
        "medium": "https://images.unsplash.com/profile-1672937944835-e59d56977ec4image?ixlib=rb-4.0.3&crop=faces&fit=crop&w=64&h=64",
        "large": "https://images.unsplash.com/profile-1672937944835-e59d56977ec4image?ixlib=rb-4.0.3&crop=faces&fit=crop&w=128&h=128"
      },
      "instagram_username": "haileylynndesigns",
      "total_collections": 0,
      "total_likes": 0,
      "total_photos": 85,
      "accepted_tos": true,
      "for_hire": true,
      "social": {
        "instagram_username": "haileylynndesigns",
        "portfolio_url": "http://haileylynndesigns.com",
        "twitter_username": null,
        "paypal_email": null
      }
    }
  },
  {
    "id": "fVUG8c1ljMs",
    "created_at": "2023-01-10T15:46:48Z",
    "updated_at": "2023-01-12T10:46:01Z",
    "promoted_at": "2023-01-12T10:42:50Z",
    "width": 3000,
    "height": 4000,
    "color": "#0c2626",
    "blur_hash": "LjF?2=%MkWtR_NozozofJoNHsoV@",
    "description": null,
    "alt_description": "a cross walk in front of a large building",
    "urls": {
      "raw": "https://images.unsplash.com/photo-1673364432867-34b2e6722181?ixid=MnwzODY1NDR8MHwxfGFsbHwzfHx8fHx8Mnx8MTY3MzUyMjY2Mg&ixlib=rb-4.0.3",
      "full": "https://images.unsplash.com/photo-1673364432867-34b2e6722181?crop=entropy&cs=tinysrgb&fm=jpg&ixid=MnwzODY1NDR8MHwxfGFsbHwzfHx8fHx8Mnx8MTY3MzUyMjY2Mg&ixlib=rb-4.0.3&q=80",
      "regular": "https://images.unsplash.com/photo-1673364432867-34b2e6722181?crop=entropy&cs=tinysrgb&fit=max&fm=jpg&ixid=MnwzODY1NDR8MHwxfGFsbHwzfHx8fHx8Mnx8MTY3MzUyMjY2Mg&ixlib=rb-4.0.3&q=80&w=1080",
      "small": "https://images.unsplash.com/photo-1673364432867-34b2e6722181?crop=entropy&cs=tinysrgb&fit=max&fm=jpg&ixid=MnwzODY1NDR8MHwxfGFsbHwzfHx8fHx8Mnx8MTY3MzUyMjY2Mg&ixlib=rb-4.0.3&q=80&w=400",
      "thumb": "https://images.unsplash.com/photo-1673364432867-34b2e6722181?crop=entropy&cs=tinysrgb&fit=max&fm=jpg&ixid=MnwzODY1NDR8MHwxfGFsbHwzfHx8fHx8Mnx8MTY3MzUyMjY2Mg&ixlib=rb-4.0.3&q=80&w=200",
      "small_s3": "https://s3.us-west-2.amazonaws.com/images.unsplash.com/small/photo-1673364432867-34b2e6722181"
    },
    "links": {
      "self": "https://api.unsplash.com/photos/fVUG8c1ljMs",
      "html": "https://unsplash.com/photos/fVUG8c1ljMs",
      "download": "https://unsplash.com/photos/fVUG8c1ljMs/download?ixid=MnwzODY1NDR8MHwxfGFsbHwzfHx8fHx8Mnx8MTY3MzUyMjY2Mg",
      "download_location": "https://api.unsplash.com/photos/fVUG8c1ljMs/download?ixid=MnwzODY1NDR8MHwxfGFsbHwzfHx8fHx8Mnx8MTY3MzUyMjY2Mg"
    },
    "likes": 9,
    "liked_by_user": false,
    "current_user_collections": [],
    "sponsorship": null,
    "topic_submissions": {},
    "user": {
      "id": "CZevM0BbJv0",
      "updated_at": "2023-01-12T10:45:17Z",
      "username": "bastien_nvs",
      "name": "Bastien Nvs",
      "first_name": "Bastien",
      "last_name": "Nvs",
      "twitter_username": null,
      "portfolio_url": "https://bastienneves.wixsite.com/bastienneves",
      "bio": "Bastien\r\n📷 | PHOTOGRAPHER & FILMMAKER 📍 | Lyon, Paris  | linktr.ee/Bastiennvs INSTAGRAM : @bastien_nvs",
      "location": "Paris",
      "links": {
        "self": "https://api.unsplash.com/users/bastien_nvs",
        "html": "https://unsplash.com/@bastien_nvs",
        "photos": "https://api.unsplash.com/users/bastien_nvs/photos",
        "likes": "https://api.unsplash.com/users/bastien_nvs/likes",
        "portfolio": "https://api.unsplash.com/users/bastien_nvs/portfolio",
        "following": "https://api.unsplash.com/users/bastien_nvs/following",
        "followers": "https://api.unsplash.com/users/bastien_nvs/followers"
      },
      "profile_image": {
        "small": "https://images.unsplash.com/profile-1648894866827-e5137814b51fimage?ixlib=rb-4.0.3&crop=faces&fit=crop&w=32&h=32",
        "medium": "https://images.unsplash.com/profile-1648894866827-e5137814b51fimage?ixlib=rb-4.0.3&crop=faces&fit=crop&w=64&h=64",
        "large": "https://images.unsplash.com/profile-1648894866827-e5137814b51fimage?ixlib=rb-4.0.3&crop=faces&fit=crop&w=128&h=128"
      },
      "instagram_username": "bastien_nvs",
      "total_collections": 2,
      "total_likes": 35,
      "total_photos": 479,
      "accepted_tos": true,
      "for_hire": true,
      "social": {
        "instagram_username": "bastien_nvs",
        "portfolio_url": "https://bastienneves.wixsite.com/bastienneves",
        "twitter_username": null,
        "paypal_email": null
      }
    }
  },
  {
    "id": "DD90tba-Uh8",
    "created_at": "2023-01-10T17:56:56Z",
    "updated_at": "2023-01-12T10:44:39Z",
    "promoted_at": "2023-01-12T10:41:31Z",
    "width": 3974,
    "height": 5961,
    "color": "#d9d9d9",
    "blur_hash": "LWHn]TKP4TRPi^o}s:oz9uv~bbxv",
    "description": null,
    "alt_description": "a long hallway with red and white walls",
    "urls": {
      "raw": "https://images.unsplash.com/photo-1673372403659-0ed2d56635b7?ixid=MnwzODY1NDR8MHwxfGFsbHw0fHx8fHx8Mnx8MTY3MzUyMjY2Mg&ixlib=rb-4.0.3",
      "full": "https://images.unsplash.com/photo-1673372403659-0ed2d56635b7?crop=entropy&cs=tinysrgb&fm=jpg&ixid=MnwzODY1NDR8MHwxfGFsbHw0fHx8fHx8Mnx8MTY3MzUyMjY2Mg&ixlib=rb-4.0.3&q=80",
      "regular": "https://images.unsplash.com/photo-1673372403659-0ed2d56635b7?crop=entropy&cs=tinysrgb&fit=max&fm=jpg&ixid=MnwzODY1NDR8MHwxfGFsbHw0fHx8fHx8Mnx8MTY3MzUyMjY2Mg&ixlib=rb-4.0.3&q=80&w=1080",
      "small": "https://images.unsplash.com/photo-1673372403659-0ed2d56635b7?crop=entropy&cs=tinysrgb&fit=max&fm=jpg&ixid=MnwzODY1NDR8MHwxfGFsbHw0fHx8fHx8Mnx8MTY3MzUyMjY2Mg&ixlib=rb-4.0.3&q=80&w=400",
      "thumb": "https://images.unsplash.com/photo-1673372403659-0ed2d56635b7?crop=entropy&cs=tinysrgb&fit=max&fm=jpg&ixid=MnwzODY1NDR8MHwxfGFsbHw0fHx8fHx8Mnx8MTY3MzUyMjY2Mg&ixlib=rb-4.0.3&q=80&w=200",
      "small_s3": "https://s3.us-west-2.amazonaws.com/images.unsplash.com/small/photo-1673372403659-0ed2d56635b7"
    },
    "links": {
      "self": "https://api.unsplash.com/photos/DD90tba-Uh8",
      "html": "https://unsplash.com/photos/DD90tba-Uh8",
      "download": "https://unsplash.com/photos/DD90tba-Uh8/download?ixid=MnwzODY1NDR8MHwxfGFsbHw0fHx8fHx8Mnx8MTY3MzUyMjY2Mg",
      "download_location": "https://api.unsplash.com/photos/DD90tba-Uh8/download?ixid=MnwzODY1NDR8MHwxfGFsbHw0fHx8fHx8Mnx8MTY3MzUyMjY2Mg"
    },
    "likes": 2,
    "liked_by_user": false,
    "current_user_collections": [],
    "sponsorship": null,
    "topic_submissions": {},
    "user": {
      "id": "XdUbKEV_2U8",
      "updated_at": "2023-01-12T10:41:31Z",
      "username": "9th_eye",
      "name": "Platon Matakaev",
      "first_name": "Platon",
      "last_name": "Matakaev",
      "twitter_username": null,
      "portfolio_url": null,
      "bio": "Hey! \r\nMy name is Platon and I am urban and street photographer. Check my Instagram to see much more content.",
      "location": "Moscow",
      "links": {
        "self": "https://api.unsplash.com/users/9th_eye",
        "html": "https://unsplash.com/de/@9th_eye",
        "photos": "https://api.unsplash.com/users/9th_eye/photos",
        "likes": "https://api.unsplash.com/users/9th_eye/likes",
        "portfolio": "https://api.unsplash.com/users/9th_eye/portfolio",
        "following": "https://api.unsplash.com/users/9th_eye/following",
        "followers": "https://api.unsplash.com/users/9th_eye/followers"
      },
      "profile_image": {
        "small": "https://images.unsplash.com/profile-1640110635750-36db292e68fbimage?ixlib=rb-4.0.3&crop=faces&fit=crop&w=32&h=32",
        "medium": "https://images.unsplash.com/profile-1640110635750-36db292e68fbimage?ixlib=rb-4.0.3&crop=faces&fit=crop&w=64&h=64",
        "large": "https://images.unsplash.com/profile-1640110635750-36db292e68fbimage?ixlib=rb-4.0.3&crop=faces&fit=crop&w=128&h=128"
      },
      "instagram_username": "9th.eye",
      "total_collections": 0,
      "total_likes": 0,
      "total_photos": 108,
      "accepted_tos": true,
      "for_hire": false,
      "social": {
        "instagram_username": "9th.eye",
        "portfolio_url": null,
        "twitter_username": null,
        "paypal_email": null
      }
    }
  },
  {
    "id": "K7FMf3G_RnQ",
    "created_at": "2023-01-08T18:20:44Z",
    "updated_at": "2023-01-12T10:44:16Z",
    "promoted_at": "2023-01-12T10:41:08Z",
    "width": 4000,
    "height": 6000,
    "color": "#260c0c",
    "blur_hash": "LC3JfBnOVYnOUHaKn3aKk?jEaKWA",
    "description": null,
    "alt_description": "a woman is seen through a rain covered window",
    "urls": {
      "raw": "https://images.unsplash.com/photo-1673201958147-959e2fc71745?ixid=MnwzODY1NDR8MHwxfGFsbHw1fHx8fHx8Mnx8MTY3MzUyMjY2Mg&ixlib=rb-4.0.3",
      "full": "https://images.unsplash.com/photo-1673201958147-959e2fc71745?crop=entropy&cs=tinysrgb&fm=jpg&ixid=MnwzODY1NDR8MHwxfGFsbHw1fHx8fHx8Mnx8MTY3MzUyMjY2Mg&ixlib=rb-4.0.3&q=80",
      "regular": "https://images.unsplash.com/photo-1673201958147-959e2fc71745?crop=entropy&cs=tinysrgb&fit=max&fm=jpg&ixid=MnwzODY1NDR8MHwxfGFsbHw1fHx8fHx8Mnx8MTY3MzUyMjY2Mg&ixlib=rb-4.0.3&q=80&w=1080",
      "small": "https://images.unsplash.com/photo-1673201958147-959e2fc71745?crop=entropy&cs=tinysrgb&fit=max&fm=jpg&ixid=MnwzODY1NDR8MHwxfGFsbHw1fHx8fHx8Mnx8MTY3MzUyMjY2Mg&ixlib=rb-4.0.3&q=80&w=400",
      "thumb": "https://images.unsplash.com/photo-1673201958147-959e2fc71745?crop=entropy&cs=tinysrgb&fit=max&fm=jpg&ixid=MnwzODY1NDR8MHwxfGFsbHw1fHx8fHx8Mnx8MTY3MzUyMjY2Mg&ixlib=rb-4.0.3&q=80&w=200",
      "small_s3": "https://s3.us-west-2.amazonaws.com/images.unsplash.com/small/photo-1673201958147-959e2fc71745"
    },
    "links": {
      "self": "https://api.unsplash.com/photos/K7FMf3G_RnQ",
      "html": "https://unsplash.com/photos/K7FMf3G_RnQ",
      "download": "https://unsplash.com/photos/K7FMf3G_RnQ/download?ixid=MnwzODY1NDR8MHwxfGFsbHw1fHx8fHx8Mnx8MTY3MzUyMjY2Mg",
      "download_location": "https://api.unsplash.com/photos/K7FMf3G_RnQ/download?ixid=MnwzODY1NDR8MHwxfGFsbHw1fHx8fHx8Mnx8MTY3MzUyMjY2Mg"
    },
    "likes": 6,
    "liked_by_user": false,
    "current_user_collections": [],
    "sponsorship": null,
    "topic_submissions": {},
    "user": {
      "id": "GHxFK4dcHGU",
      "updated_at": "2023-01-12T10:43:47Z",
      "username": "alex__grig",
      "name": "Alexander Grigoryev",
      "first_name": "Alexander",
      "last_name": "Grigoryev",
      "twitter_username": "Alex__Grig",
      "portfolio_url": "https://www.instagram.com/alex__grig/",
      "bio": null,
      "location": "Saint-Petersburg",
      "links": {
        "self": "https://api.unsplash.com/users/alex__grig",
        "html": "https://unsplash.com/@alex__grig",
        "photos": "https://api.unsplash.com/users/alex__grig/photos",
        "likes": "https://api.unsplash.com/users/alex__grig/likes",
        "portfolio": "https://api.unsplash.com/users/alex__grig/portfolio",
        "following": "https://api.unsplash.com/users/alex__grig/following",
        "followers": "https://api.unsplash.com/users/alex__grig/followers"
      },
      "profile_image": {
        "small": "https://images.unsplash.com/profile-1601631013359-a8c0112495a1image?ixlib=rb-4.0.3&crop=faces&fit=crop&w=32&h=32",
        "medium": "https://images.unsplash.com/profile-1601631013359-a8c0112495a1image?ixlib=rb-4.0.3&crop=faces&fit=crop&w=64&h=64",
        "large": "https://images.unsplash.com/profile-1601631013359-a8c0112495a1image?ixlib=rb-4.0.3&crop=faces&fit=crop&w=128&h=128"
      },
      "instagram_username": "Alex__Grig",
      "total_collections": 0,
      "total_likes": 23,
      "total_photos": 298,
      "accepted_tos": true,
      "for_hire": true,
      "social": {
        "instagram_username": "Alex__Grig",
        "portfolio_url": "https://www.instagram.com/alex__grig/",
        "twitter_username": "Alex__Grig",
        "paypal_email": null
      }
    }
  },
  {
    "id": "uifTyG8vUCk",
    "created_at": "2022-08-31T15:52:30Z",
    "updated_at": "2023-01-11T18:34:07Z",
    "promoted_at": null,
    "width": 6048,
    "height": 4024,
    "color": "#594026",
    "blur_hash": "LWIgAFf,WB^d~8=_WCt6EL=^t6Iu",
    "description": null,
    "alt_description": null,
    "urls": {
      "raw": "https://images.unsplash.com/photo-1661961111184-11317b40adb2?ixid=MnwzODY1NDR8MXwxfGFsbHw2fHx8fHx8Mnx8MTY3MzUyMjY2Mg&ixlib=rb-4.0.3",
      "full": "https://images.unsplash.com/photo-1661961111184-11317b40adb2?crop=entropy&cs=tinysrgb&fm=jpg&ixid=MnwzODY1NDR8MXwxfGFsbHw2fHx8fHx8Mnx8MTY3MzUyMjY2Mg&ixlib=rb-4.0.3&q=80",
      "regular": "https://images.unsplash.com/photo-1661961111184-11317b40adb2?crop=entropy&cs=tinysrgb&fit=max&fm=jpg&ixid=MnwzODY1NDR8MXwxfGFsbHw2fHx8fHx8Mnx8MTY3MzUyMjY2Mg&ixlib=rb-4.0.3&q=80&w=1080",
      "small": "https://images.unsplash.com/photo-1661961111184-11317b40adb2?crop=entropy&cs=tinysrgb&fit=max&fm=jpg&ixid=MnwzODY1NDR8MXwxfGFsbHw2fHx8fHx8Mnx8MTY3MzUyMjY2Mg&ixlib=rb-4.0.3&q=80&w=400",
      "thumb": "https://images.unsplash.com/photo-1661961111184-11317b40adb2?crop=entropy&cs=tinysrgb&fit=max&fm=jpg&ixid=MnwzODY1NDR8MXwxfGFsbHw2fHx8fHx8Mnx8MTY3MzUyMjY2Mg&ixlib=rb-4.0.3&q=80&w=200",
      "small_s3": "https://s3.us-west-2.amazonaws.com/images.unsplash.com/small/photo-1661961111184-11317b40adb2"
    },
    "links": {
      "self": "https://api.unsplash.com/photos/uifTyG8vUCk",
      "html": "https://unsplash.com/photos/uifTyG8vUCk",
      "download": "https://unsplash.com/photos/uifTyG8vUCk/download?ixid=MnwzODY1NDR8MXwxfGFsbHw2fHx8fHx8Mnx8MTY3MzUyMjY2Mg",
      "download_location": "https://api.unsplash.com/photos/uifTyG8vUCk/download?ixid=MnwzODY1NDR8MXwxfGFsbHw2fHx8fHx8Mnx8MTY3MzUyMjY2Mg"
    },
    "likes": 162,
    "liked_by_user": false,
    "current_user_collections": [],
    "sponsorship": {
      "impression_urls": [
        "https://secure.insightexpressai.com/adServer/adServerESI.aspx?script=false&bannerID=10716800&rnd=[timestamp]&redir=https://secure.insightexpressai.com/adserver/1pixel.gif",
        "https://ad.doubleclick.net/ddm/trackimp/N1153793.3286893UNSPLASH/B28763390.348954720;dc_trk_aid=541060625;dc_trk_cid=180308083;ord=[timestamp];dc_lat=;dc_rdid=;tag_for_child_directed_treatment=;tfua=;gdpr=${GDPR};gdpr_consent=${GDPR_CONSENT_755};ltd=?",
        "https://tps.doubleverify.com/visit.jpg?ctx=569086&cmp=28763390&sid=6781114&plc=348954720&adsrv=1&btreg=&btadsrv=&crt=&tagtype=&dvtagver=6.1.img&"
      ],
      "tagline": "Unlock your potential on Windows 11 and Microsoft 365",
      "tagline_url": "https://ad.doubleclick.net/ddm/trackclk/N1153793.3286893UNSPLASH/B28763390.348954720;dc_trk_aid=541060625;dc_trk_cid=180308083;dc_lat=;dc_rdid=;tag_for_child_directed_treatment=;tfua=;ltd=",
      "sponsor": {
        "id": "kSlnstJTnY8",
        "updated_at": "2023-01-12T09:18:13Z",
        "username": "windows",
        "name": "Windows",
        "first_name": "Windows",
        "last_name": null,
        "twitter_username": "windows",
        "portfolio_url": "https://www.windows.com",
        "bio": "Makes the everyday easier.",
        "location": null,
        "links": {
          "self": "https://api.unsplash.com/users/windows",
          "html": "https://unsplash.com/@windows",
          "photos": "https://api.unsplash.com/users/windows/photos",
          "likes": "https://api.unsplash.com/users/windows/likes",
          "portfolio": "https://api.unsplash.com/users/windows/portfolio",
          "following": "https://api.unsplash.com/users/windows/following",
          "followers": "https://api.unsplash.com/users/windows/followers"
        },
        "profile_image": {
          "small": "https://images.unsplash.com/profile-1633364056312-0319b9fc4586image?ixlib=rb-4.0.3&crop=faces&fit=crop&w=32&h=32",
          "medium": "https://images.unsplash.com/profile-1633364056312-0319b9fc4586image?ixlib=rb-4.0.3&crop=faces&fit=crop&w=64&h=64",
          "large": "https://images.unsplash.com/profile-1633364056312-0319b9fc4586image?ixlib=rb-4.0.3&crop=faces&fit=crop&w=128&h=128"
        },
        "instagram_username": "windows",
        "total_collections": 1,
        "total_likes": 0,
        "total_photos": 186,
        "accepted_tos": true,
        "for_hire": false,
        "social": {
          "instagram_username": "windows",
          "portfolio_url": "https://www.windows.com",
          "twitter_username": "windows",
          "paypal_email": null
        }
      }
    },
    "topic_submissions": {},
    "user": {
      "id": "2DC3GyeqWjI",
      "updated_at": "2023-01-11T17:51:28Z",
      "username": "dell",
      "name": "Dell",
      "first_name": "Dell",
      "last_name": null,
      "twitter_username": "Dell",
      "portfolio_url": "http://www.dell.com/xps",
      "bio": "Designed to be the best, with cutting edge technologies, exceptional build quality, unique materials and powerful features.",
      "location": null,
      "links": {
        "self": "https://api.unsplash.com/users/dell",
        "html": "https://unsplash.com/@dell",
        "photos": "https://api.unsplash.com/users/dell/photos",
        "likes": "https://api.unsplash.com/users/dell/likes",
        "portfolio": "https://api.unsplash.com/users/dell/portfolio",
        "following": "https://api.unsplash.com/users/dell/following",
        "followers": "https://api.unsplash.com/users/dell/followers"
      },
      "profile_image": {
        "small": "https://images.unsplash.com/profile-1660078756938-1f3564bcf935image?ixlib=rb-4.0.3&crop=faces&fit=crop&w=32&h=32",
        "medium": "https://images.unsplash.com/profile-1660078756938-1f3564bcf935image?ixlib=rb-4.0.3&crop=faces&fit=crop&w=64&h=64",
        "large": "https://images.unsplash.com/profile-1660078756938-1f3564bcf935image?ixlib=rb-4.0.3&crop=faces&fit=crop&w=128&h=128"
      },
      "instagram_username": "dell",
      "total_collections": 0,
      "total_likes": 0,
      "total_photos": 35,
      "accepted_tos": true,
      "for_hire": false,
      "social": {
        "instagram_username": "dell",
        "portfolio_url": "http://www.dell.com/xps",
        "twitter_username": "Dell",
        "paypal_email": null
      }
    }
  },
  {
    "id": "cWGthgrcBS0",
    "created_at": "2023-01-10T17:56:56Z",
    "updated_at": "2023-01-12T10:44:00Z",
    "promoted_at": "2023-01-12T10:40:57Z",
    "width": 3977,
    "height": 5965,
    "color": "#f3f3f3",
    "blur_hash": "LxHx+?jZIUj[~qfPR*ay%gofofV@",
    "description": null,
    "alt_description": "a car driving down a street next to tall buildings",
    "urls": {
      "raw": "https://images.unsplash.com/photo-1673372267880-bc6914e446cb?ixid=MnwzODY1NDR8MHwxfGFsbHw3fHx8fHx8Mnx8MTY3MzUyMjY2Mg&ixlib=rb-4.0.3",
      "full": "https://images.unsplash.com/photo-1673372267880-bc6914e446cb?crop=entropy&cs=tinysrgb&fm=jpg&ixid=MnwzODY1NDR8MHwxfGFsbHw3fHx8fHx8Mnx8MTY3MzUyMjY2Mg&ixlib=rb-4.0.3&q=80",
      "regular": "https://images.unsplash.com/photo-1673372267880-bc6914e446cb?crop=entropy&cs=tinysrgb&fit=max&fm=jpg&ixid=MnwzODY1NDR8MHwxfGFsbHw3fHx8fHx8Mnx8MTY3MzUyMjY2Mg&ixlib=rb-4.0.3&q=80&w=1080",
      "small": "https://images.unsplash.com/photo-1673372267880-bc6914e446cb?crop=entropy&cs=tinysrgb&fit=max&fm=jpg&ixid=MnwzODY1NDR8MHwxfGFsbHw3fHx8fHx8Mnx8MTY3MzUyMjY2Mg&ixlib=rb-4.0.3&q=80&w=400",
      "thumb": "https://images.unsplash.com/photo-1673372267880-bc6914e446cb?crop=entropy&cs=tinysrgb&fit=max&fm=jpg&ixid=MnwzODY1NDR8MHwxfGFsbHw3fHx8fHx8Mnx8MTY3MzUyMjY2Mg&ixlib=rb-4.0.3&q=80&w=200",
      "small_s3": "https://s3.us-west-2.amazonaws.com/images.unsplash.com/small/photo-1673372267880-bc6914e446cb"
    },
    "links": {
      "self": "https://api.unsplash.com/photos/cWGthgrcBS0",
      "html": "https://unsplash.com/photos/cWGthgrcBS0",
      "download": "https://unsplash.com/photos/cWGthgrcBS0/download?ixid=MnwzODY1NDR8MHwxfGFsbHw3fHx8fHx8Mnx8MTY3MzUyMjY2Mg",
      "download_location": "https://api.unsplash.com/photos/cWGthgrcBS0/download?ixid=MnwzODY1NDR8MHwxfGFsbHw3fHx8fHx8Mnx8MTY3MzUyMjY2Mg"
    },
    "likes": 2,
    "liked_by_user": false,
    "current_user_collections": [],
    "sponsorship": null,
    "topic_submissions": {},
    "user": {
      "id": "XdUbKEV_2U8",
      "updated_at": "2023-01-12T10:41:31Z",
      "username": "9th_eye",
      "name": "Platon Matakaev",
      "first_name": "Platon",
      "last_name": "Matakaev",
      "twitter_username": null,
      "portfolio_url": null,
      "bio": "Hey! \r\nMy name is Platon and I am urban and street photographer. Check my Instagram to see much more content.",
      "location": "Moscow",
      "links": {
        "self": "https://api.unsplash.com/users/9th_eye",
        "html": "https://unsplash.com/de/@9th_eye",
        "photos": "https://api.unsplash.com/users/9th_eye/photos",
        "likes": "https://api.unsplash.com/users/9th_eye/likes",
        "portfolio": "https://api.unsplash.com/users/9th_eye/portfolio",
        "following": "https://api.unsplash.com/users/9th_eye/following",
        "followers": "https://api.unsplash.com/users/9th_eye/followers"
      },
      "profile_image": {
        "small": "https://images.unsplash.com/profile-1640110635750-36db292e68fbimage?ixlib=rb-4.0.3&crop=faces&fit=crop&w=32&h=32",
        "medium": "https://images.unsplash.com/profile-1640110635750-36db292e68fbimage?ixlib=rb-4.0.3&crop=faces&fit=crop&w=64&h=64",
        "large": "https://images.unsplash.com/profile-1640110635750-36db292e68fbimage?ixlib=rb-4.0.3&crop=faces&fit=crop&w=128&h=128"
      },
      "instagram_username": "9th.eye",
      "total_collections": 0,
      "total_likes": 0,
      "total_photos": 108,
      "accepted_tos": true,
      "for_hire": false,
      "social": {
        "instagram_username": "9th.eye",
        "portfolio_url": null,
        "twitter_username": null,
        "paypal_email": null
      }
    }
  },
  {
    "id": "H_KizCd6Zqs",
    "created_at": "2023-01-09T20:53:01Z",
    "updated_at": "2023-01-12T10:43:53Z",
    "promoted_at": "2023-01-12T10:40:53Z",
    "width": 5472,
    "height": 3648,
    "color": "#262626",
    "blur_hash": "LfEx;9t6IpWC~Vt6RjWCx]oejFWC",
    "description": null,
    "alt_description": "a field full of red flowers under a cloudy sky",
    "urls": {
      "raw": "https://images.unsplash.com/photo-1673297251584-97d09e1e6b54?ixid=MnwzODY1NDR8MHwxfGFsbHw4fHx8fHx8Mnx8MTY3MzUyMjY2Mg&ixlib=rb-4.0.3",
      "full": "https://images.unsplash.com/photo-1673297251584-97d09e1e6b54?crop=entropy&cs=tinysrgb&fm=jpg&ixid=MnwzODY1NDR8MHwxfGFsbHw4fHx8fHx8Mnx8MTY3MzUyMjY2Mg&ixlib=rb-4.0.3&q=80",
      "regular": "https://images.unsplash.com/photo-1673297251584-97d09e1e6b54?crop=entropy&cs=tinysrgb&fit=max&fm=jpg&ixid=MnwzODY1NDR8MHwxfGFsbHw4fHx8fHx8Mnx8MTY3MzUyMjY2Mg&ixlib=rb-4.0.3&q=80&w=1080",
      "small": "https://images.unsplash.com/photo-1673297251584-97d09e1e6b54?crop=entropy&cs=tinysrgb&fit=max&fm=jpg&ixid=MnwzODY1NDR8MHwxfGFsbHw4fHx8fHx8Mnx8MTY3MzUyMjY2Mg&ixlib=rb-4.0.3&q=80&w=400",
      "thumb": "https://images.unsplash.com/photo-1673297251584-97d09e1e6b54?crop=entropy&cs=tinysrgb&fit=max&fm=jpg&ixid=MnwzODY1NDR8MHwxfGFsbHw4fHx8fHx8Mnx8MTY3MzUyMjY2Mg&ixlib=rb-4.0.3&q=80&w=200",
      "small_s3": "https://s3.us-west-2.amazonaws.com/images.unsplash.com/small/photo-1673297251584-97d09e1e6b54"
    },
    "links": {
      "self": "https://api.unsplash.com/photos/H_KizCd6Zqs",
      "html": "https://unsplash.com/photos/H_KizCd6Zqs",
      "download": "https://unsplash.com/photos/H_KizCd6Zqs/download?ixid=MnwzODY1NDR8MHwxfGFsbHw4fHx8fHx8Mnx8MTY3MzUyMjY2Mg",
      "download_location": "https://api.unsplash.com/photos/H_KizCd6Zqs/download?ixid=MnwzODY1NDR8MHwxfGFsbHw4fHx8fHx8Mnx8MTY3MzUyMjY2Mg"
    },
    "likes": 2,
    "liked_by_user": false,
    "current_user_collections": [],
    "sponsorship": null,
    "topic_submissions": {},
    "user": {
      "id": "JoxIOp97IUU",
      "updated_at": "2023-01-12T10:52:15Z",
      "username": "sylvester_s",
      "name": "Sylvester Sabo",
      "first_name": "Sylvester",
      "last_name": "Sabo",
      "twitter_username": null,
      "portfolio_url": null,
      "bio": null,
      "location": null,
      "links": {
        "self": "https://api.unsplash.com/users/sylvester_s",
        "html": "https://unsplash.com/ko/@sylvester_s",
        "photos": "https://api.unsplash.com/users/sylvester_s/photos",
        "likes": "https://api.unsplash.com/users/sylvester_s/likes",
        "portfolio": "https://api.unsplash.com/users/sylvester_s/portfolio",
        "following": "https://api.unsplash.com/users/sylvester_s/following",
        "followers": "https://api.unsplash.com/users/sylvester_s/followers"
      },
      "profile_image": {
        "small": "https://images.unsplash.com/profile-fb-1591370305-f51a46aec538.jpg?ixlib=rb-4.0.3&crop=faces&fit=crop&w=32&h=32",
        "medium": "https://images.unsplash.com/profile-fb-1591370305-f51a46aec538.jpg?ixlib=rb-4.0.3&crop=faces&fit=crop&w=64&h=64",
        "large": "https://images.unsplash.com/profile-fb-1591370305-f51a46aec538.jpg?ixlib=rb-4.0.3&crop=faces&fit=crop&w=128&h=128"
      },
      "instagram_username": null,
      "total_collections": 0,
      "total_likes": 0,
      "total_photos": 193,
      "accepted_tos": true,
      "for_hire": false,
      "social": {
        "instagram_username": null,
        "portfolio_url": null,
        "twitter_username": null,
        "paypal_email": null
      }
    }
  },
  {
    "id": "851kICtFyXc",
    "created_at": "2023-01-09T11:27:21Z",
    "updated_at": "2023-01-12T10:43:37Z",
    "promoted_at": "2023-01-12T10:40:36Z",
    "width": 6000,
    "height": 4000,
    "color": "#262626",
    "blur_hash": "L36*aWt74.oL01WC%2t7?bV@M{Rj",
    "description": null,
    "alt_description": "a statue of a deer on top of a rock",
    "urls": {
      "raw": "https://images.unsplash.com/photo-1673263229942-1d26f16ecd1a?ixid=MnwzODY1NDR8MHwxfGFsbHw5fHx8fHx8Mnx8MTY3MzUyMjY2Mg&ixlib=rb-4.0.3",
      "full": "https://images.unsplash.com/photo-1673263229942-1d26f16ecd1a?crop=entropy&cs=tinysrgb&fm=jpg&ixid=MnwzODY1NDR8MHwxfGFsbHw5fHx8fHx8Mnx8MTY3MzUyMjY2Mg&ixlib=rb-4.0.3&q=80",
      "regular": "https://images.unsplash.com/photo-1673263229942-1d26f16ecd1a?crop=entropy&cs=tinysrgb&fit=max&fm=jpg&ixid=MnwzODY1NDR8MHwxfGFsbHw5fHx8fHx8Mnx8MTY3MzUyMjY2Mg&ixlib=rb-4.0.3&q=80&w=1080",
      "small": "https://images.unsplash.com/photo-1673263229942-1d26f16ecd1a?crop=entropy&cs=tinysrgb&fit=max&fm=jpg&ixid=MnwzODY1NDR8MHwxfGFsbHw5fHx8fHx8Mnx8MTY3MzUyMjY2Mg&ixlib=rb-4.0.3&q=80&w=400",
      "thumb": "https://images.unsplash.com/photo-1673263229942-1d26f16ecd1a?crop=entropy&cs=tinysrgb&fit=max&fm=jpg&ixid=MnwzODY1NDR8MHwxfGFsbHw5fHx8fHx8Mnx8MTY3MzUyMjY2Mg&ixlib=rb-4.0.3&q=80&w=200",
      "small_s3": "https://s3.us-west-2.amazonaws.com/images.unsplash.com/small/photo-1673263229942-1d26f16ecd1a"
    },
    "links": {
      "self": "https://api.unsplash.com/photos/851kICtFyXc",
      "html": "https://unsplash.com/photos/851kICtFyXc",
      "download": "https://unsplash.com/photos/851kICtFyXc/download?ixid=MnwzODY1NDR8MHwxfGFsbHw5fHx8fHx8Mnx8MTY3MzUyMjY2Mg",
      "download_location": "https://api.unsplash.com/photos/851kICtFyXc/download?ixid=MnwzODY1NDR8MHwxfGFsbHw5fHx8fHx8Mnx8MTY3MzUyMjY2Mg"
    },
    "likes": 1,
    "liked_by_user": false,
    "current_user_collections": [],
    "sponsorship": null,
    "topic_submissions": {},
    "user": {
      "id": "IPXJAnYBKHk",
      "updated_at": "2023-01-12T10:43:47Z",
      "username": "julianhochgesang",
      "name": "Julian Hochgesang",
      "first_name": "Julian",
      "last_name": "Hochgesang",
      "twitter_username": null,
      "portfolio_url": null,
      "bio": "Contemporary and slowing photography in a modern, fast moving world.",
      "location": "Bavaria, Germany",
      "links": {
        "self": "https://api.unsplash.com/users/julianhochgesang",
        "html": "https://unsplash.com/@julianhochgesang",
        "photos": "https://api.unsplash.com/users/julianhochgesang/photos",
        "likes": "https://api.unsplash.com/users/julianhochgesang/likes",
        "portfolio": "https://api.unsplash.com/users/julianhochgesang/portfolio",
        "following": "https://api.unsplash.com/users/julianhochgesang/following",
        "followers": "https://api.unsplash.com/users/julianhochgesang/followers"
      },
      "profile_image": {
        "small": "https://images.unsplash.com/profile-1562792613192-dbd072779970?ixlib=rb-4.0.3&crop=faces&fit=crop&w=32&h=32",
        "medium": "https://images.unsplash.com/profile-1562792613192-dbd072779970?ixlib=rb-4.0.3&crop=faces&fit=crop&w=64&h=64",
        "large": "https://images.unsplash.com/profile-1562792613192-dbd072779970?ixlib=rb-4.0.3&crop=faces&fit=crop&w=128&h=128"
      },
      "instagram_username": "julianhochgesang",
      "total_collections": 2,
      "total_likes": 1974,
      "total_photos": 589,
      "accepted_tos": true,
      "for_hire": true,
      "social": {
        "instagram_username": "julianhochgesang",
        "portfolio_url": null,
        "twitter_username": null,
        "paypal_email": null
      }
    }
  },
  {
    "id": "tKRCEBZEIDI",
    "created_at": "2023-01-10T16:22:07Z",
    "updated_at": "2023-01-12T10:42:12Z",
    "promoted_at": "2023-01-12T10:39:11Z",
    "width": 7008,
    "height": 4672,
    "color": "#f3d9d9",
    "blur_hash": "L;HnmX-oM{oe~WxaRjof%3RkWVof",
    "description": null,
    "alt_description": "a view of a mountain with trees in the foreground",
    "urls": {
      "raw": "https://images.unsplash.com/photo-1673367620868-585f0613c9a2?ixid=MnwzODY1NDR8MHwxfGFsbHwxMHx8fHx8fDJ8fDE2NzM1MjI2NjI&ixlib=rb-4.0.3",
      "full": "https://images.unsplash.com/photo-1673367620868-585f0613c9a2?crop=entropy&cs=tinysrgb&fm=jpg&ixid=MnwzODY1NDR8MHwxfGFsbHwxMHx8fHx8fDJ8fDE2NzM1MjI2NjI&ixlib=rb-4.0.3&q=80",
      "regular": "https://images.unsplash.com/photo-1673367620868-585f0613c9a2?crop=entropy&cs=tinysrgb&fit=max&fm=jpg&ixid=MnwzODY1NDR8MHwxfGFsbHwxMHx8fHx8fDJ8fDE2NzM1MjI2NjI&ixlib=rb-4.0.3&q=80&w=1080",
      "small": "https://images.unsplash.com/photo-1673367620868-585f0613c9a2?crop=entropy&cs=tinysrgb&fit=max&fm=jpg&ixid=MnwzODY1NDR8MHwxfGFsbHwxMHx8fHx8fDJ8fDE2NzM1MjI2NjI&ixlib=rb-4.0.3&q=80&w=400",
      "thumb": "https://images.unsplash.com/photo-1673367620868-585f0613c9a2?crop=entropy&cs=tinysrgb&fit=max&fm=jpg&ixid=MnwzODY1NDR8MHwxfGFsbHwxMHx8fHx8fDJ8fDE2NzM1MjI2NjI&ixlib=rb-4.0.3&q=80&w=200",
      "small_s3": "https://s3.us-west-2.amazonaws.com/images.unsplash.com/small/photo-1673367620868-585f0613c9a2"
    },
    "links": {
      "self": "https://api.unsplash.com/photos/tKRCEBZEIDI",
      "html": "https://unsplash.com/photos/tKRCEBZEIDI",
      "download": "https://unsplash.com/photos/tKRCEBZEIDI/download?ixid=MnwzODY1NDR8MHwxfGFsbHwxMHx8fHx8fDJ8fDE2NzM1MjI2NjI",
      "download_location": "https://api.unsplash.com/photos/tKRCEBZEIDI/download?ixid=MnwzODY1NDR8MHwxfGFsbHwxMHx8fHx8fDJ8fDE2NzM1MjI2NjI"
    },
    "likes": 2,
    "liked_by_user": false,
    "current_user_collections": [],
    "sponsorship": null,
    "topic_submissions": {},
    "user": {
      "id": "LFAqEFGaEBE",
      "updated_at": "2023-01-12T10:43:46Z",
      "username": "matnapo",
      "name": "Mat Napo",
      "first_name": "Mat",
      "last_name": "Napo",
      "twitter_username": null,
      "portfolio_url": null,
      "bio": null,
      "location": "Paris",
      "links": {
        "self": "https://api.unsplash.com/users/matnapo",
        "html": "https://unsplash.com/@matnapo",
        "photos": "https://api.unsplash.com/users/matnapo/photos",
        "likes": "https://api.unsplash.com/users/matnapo/likes",
        "portfolio": "https://api.unsplash.com/users/matnapo/portfolio",
        "following": "https://api.unsplash.com/users/matnapo/following",
        "followers": "https://api.unsplash.com/users/matnapo/followers"
      },
      "profile_image": {
        "small": "https://images.unsplash.com/profile-1615632965835-1c52963ced8dimage?ixlib=rb-4.0.3&crop=faces&fit=crop&w=32&h=32",
        "medium": "https://images.unsplash.com/profile-1615632965835-1c52963ced8dimage?ixlib=rb-4.0.3&crop=faces&fit=crop&w=64&h=64",
        "large": "https://images.unsplash.com/profile-1615632965835-1c52963ced8dimage?ixlib=rb-4.0.3&crop=faces&fit=crop&w=128&h=128"
      },
      "instagram_username": "matnapo",
      "total_collections": 0,
      "total_likes": 13,
      "total_photos": 207,
      "accepted_tos": true,
      "for_hire": true,
      "social": {
        "instagram_username": "matnapo",
        "portfolio_url": null,
        "twitter_username": null,
        "paypal_email": null
      }
    }
  },
  {
    "id": "JdVWgsh4Rag",
    "created_at": "2022-12-22T16:24:23Z",
    "updated_at": "2023-01-11T21:36:25Z",
    "promoted_at": null,
    "width": 4945,
    "height": 7410,
    "color": "#a6a6a6",
    "blur_hash": "LFIhy%adslRP_NIUbwkCH=xtoKoJ",
    "description": null,
    "alt_description": "a table that has a laptop on it",
    "urls": {
      "raw": "https://images.unsplash.com/photo-1671726203402-fd8674fd3c96?ixid=MnwzODY1NDR8MXwxfGFsbHwxMXx8fHx8fDJ8fDE2NzM1MjI2NjI&ixlib=rb-4.0.3",
      "full": "https://images.unsplash.com/photo-1671726203402-fd8674fd3c96?crop=entropy&cs=tinysrgb&fm=jpg&ixid=MnwzODY1NDR8MXwxfGFsbHwxMXx8fHx8fDJ8fDE2NzM1MjI2NjI&ixlib=rb-4.0.3&q=80",
      "regular": "https://images.unsplash.com/photo-1671726203402-fd8674fd3c96?crop=entropy&cs=tinysrgb&fit=max&fm=jpg&ixid=MnwzODY1NDR8MXwxfGFsbHwxMXx8fHx8fDJ8fDE2NzM1MjI2NjI&ixlib=rb-4.0.3&q=80&w=1080",
      "small": "https://images.unsplash.com/photo-1671726203402-fd8674fd3c96?crop=entropy&cs=tinysrgb&fit=max&fm=jpg&ixid=MnwzODY1NDR8MXwxfGFsbHwxMXx8fHx8fDJ8fDE2NzM1MjI2NjI&ixlib=rb-4.0.3&q=80&w=400",
      "thumb": "https://images.unsplash.com/photo-1671726203402-fd8674fd3c96?crop=entropy&cs=tinysrgb&fit=max&fm=jpg&ixid=MnwzODY1NDR8MXwxfGFsbHwxMXx8fHx8fDJ8fDE2NzM1MjI2NjI&ixlib=rb-4.0.3&q=80&w=200",
      "small_s3": "https://s3.us-west-2.amazonaws.com/images.unsplash.com/small/photo-1671726203402-fd8674fd3c96"
    },
    "links": {
      "self": "https://api.unsplash.com/photos/JdVWgsh4Rag",
      "html": "https://unsplash.com/photos/JdVWgsh4Rag",
      "download": "https://unsplash.com/photos/JdVWgsh4Rag/download?ixid=MnwzODY1NDR8MXwxfGFsbHwxMXx8fHx8fDJ8fDE2NzM1MjI2NjI",
      "download_location": "https://api.unsplash.com/photos/JdVWgsh4Rag/download?ixid=MnwzODY1NDR8MXwxfGFsbHwxMXx8fHx8fDJ8fDE2NzM1MjI2NjI"
    },
    "likes": 4,
    "liked_by_user": false,
    "current_user_collections": [],
    "sponsorship": {
      "impression_urls": [
        "https://secure.insightexpressai.com/adServer/adServerESI.aspx?script=false&bannerID=11051526&rnd=[timestamp]&redir=https://secure.insightexpressai.com/adserver/1pixel.gif"
      ],
      "tagline": "Laptops Designed by Microsoft",
      "tagline_url": "https://www.microsoft.com/surface?ocid=UnsplashFY23_soc_pmc_sur_",
      "sponsor": {
        "id": "N-JSeSTCz68",
        "updated_at": "2023-01-12T07:41:56Z",
        "username": "surface",
        "name": "Surface",
        "first_name": "Surface",
        "last_name": null,
        "twitter_username": "surface",
        "portfolio_url": "http://surface.com",
        "bio": "Follow us @Surface – Laptops designed by Microsoft",
        "location": null,
        "links": {
          "self": "https://api.unsplash.com/users/surface",
          "html": "https://unsplash.com/ko/@surface",
          "photos": "https://api.unsplash.com/users/surface/photos",
          "likes": "https://api.unsplash.com/users/surface/likes",
          "portfolio": "https://api.unsplash.com/users/surface/portfolio",
          "following": "https://api.unsplash.com/users/surface/following",
          "followers": "https://api.unsplash.com/users/surface/followers"
        },
        "profile_image": {
          "small": "https://images.unsplash.com/profile-1587651800415-20eed2ec0209image?ixlib=rb-4.0.3&crop=faces&fit=crop&w=32&h=32",
          "medium": "https://images.unsplash.com/profile-1587651800415-20eed2ec0209image?ixlib=rb-4.0.3&crop=faces&fit=crop&w=64&h=64",
          "large": "https://images.unsplash.com/profile-1587651800415-20eed2ec0209image?ixlib=rb-4.0.3&crop=faces&fit=crop&w=128&h=128"
        },
        "instagram_username": "surface",
        "total_collections": 6,
        "total_likes": 0,
        "total_photos": 301,
        "accepted_tos": true,
        "for_hire": false,
        "social": {
          "instagram_username": "surface",
          "portfolio_url": "http://surface.com",
          "twitter_username": "surface",
          "paypal_email": null
        }
      }
    },
    "topic_submissions": {},
    "user": {
      "id": "N-JSeSTCz68",
      "updated_at": "2023-01-12T07:41:56Z",
      "username": "surface",
      "name": "Surface",
      "first_name": "Surface",
      "last_name": null,
      "twitter_username": "surface",
      "portfolio_url": "http://surface.com",
      "bio": "Follow us @Surface – Laptops designed by Microsoft",
      "location": null,
      "links": {
        "self": "https://api.unsplash.com/users/surface",
        "html": "https://unsplash.com/ko/@surface",
        "photos": "https://api.unsplash.com/users/surface/photos",
        "likes": "https://api.unsplash.com/users/surface/likes",
        "portfolio": "https://api.unsplash.com/users/surface/portfolio",
        "following": "https://api.unsplash.com/users/surface/following",
        "followers": "https://api.unsplash.com/users/surface/followers"
      },
      "profile_image": {
        "small": "https://images.unsplash.com/profile-1587651800415-20eed2ec0209image?ixlib=rb-4.0.3&crop=faces&fit=crop&w=32&h=32",
        "medium": "https://images.unsplash.com/profile-1587651800415-20eed2ec0209image?ixlib=rb-4.0.3&crop=faces&fit=crop&w=64&h=64",
        "large": "https://images.unsplash.com/profile-1587651800415-20eed2ec0209image?ixlib=rb-4.0.3&crop=faces&fit=crop&w=128&h=128"
      },
      "instagram_username": "surface",
      "total_collections": 6,
      "total_likes": 0,
      "total_photos": 301,
      "accepted_tos": true,
      "for_hire": false,
      "social": {
        "instagram_username": "surface",
        "portfolio_url": "http://surface.com",
        "twitter_username": "surface",
        "paypal_email": null
      }
    }
  },
  {
    "id": "ZXpWhhWR4U0",
    "created_at": "2023-01-10T17:13:41Z",
    "updated_at": "2023-01-12T10:41:16Z",
    "promoted_at": "2023-01-12T10:38:12Z",
    "width": 5536,
    "height": 4160,
    "color": "#262626",
    "blur_hash": "LWD+h@~VNGE2xtofWCbHNdS4s.xG",
    "description": null,
    "alt_description": "a building with a green awning and a sign on the front of it",
    "urls": {
      "raw": "https://images.unsplash.com/photo-1673370764129-c59895be12fa?ixid=MnwzODY1NDR8MHwxfGFsbHwxMnx8fHx8fDJ8fDE2NzM1MjI2NjI&ixlib=rb-4.0.3",
      "full": "https://images.unsplash.com/photo-1673370764129-c59895be12fa?crop=entropy&cs=tinysrgb&fm=jpg&ixid=MnwzODY1NDR8MHwxfGFsbHwxMnx8fHx8fDJ8fDE2NzM1MjI2NjI&ixlib=rb-4.0.3&q=80",
      "regular": "https://images.unsplash.com/photo-1673370764129-c59895be12fa?crop=entropy&cs=tinysrgb&fit=max&fm=jpg&ixid=MnwzODY1NDR8MHwxfGFsbHwxMnx8fHx8fDJ8fDE2NzM1MjI2NjI&ixlib=rb-4.0.3&q=80&w=1080",
      "small": "https://images.unsplash.com/photo-1673370764129-c59895be12fa?crop=entropy&cs=tinysrgb&fit=max&fm=jpg&ixid=MnwzODY1NDR8MHwxfGFsbHwxMnx8fHx8fDJ8fDE2NzM1MjI2NjI&ixlib=rb-4.0.3&q=80&w=400",
      "thumb": "https://images.unsplash.com/photo-1673370764129-c59895be12fa?crop=entropy&cs=tinysrgb&fit=max&fm=jpg&ixid=MnwzODY1NDR8MHwxfGFsbHwxMnx8fHx8fDJ8fDE2NzM1MjI2NjI&ixlib=rb-4.0.3&q=80&w=200",
      "small_s3": "https://s3.us-west-2.amazonaws.com/images.unsplash.com/small/photo-1673370764129-c59895be12fa"
    },
    "links": {
      "self": "https://api.unsplash.com/photos/ZXpWhhWR4U0",
      "html": "https://unsplash.com/photos/ZXpWhhWR4U0",
      "download": "https://unsplash.com/photos/ZXpWhhWR4U0/download?ixid=MnwzODY1NDR8MHwxfGFsbHwxMnx8fHx8fDJ8fDE2NzM1MjI2NjI",
      "download_location": "https://api.unsplash.com/photos/ZXpWhhWR4U0/download?ixid=MnwzODY1NDR8MHwxfGFsbHwxMnx8fHx8fDJ8fDE2NzM1MjI2NjI"
    },
    "likes": 1,
    "liked_by_user": false,
    "current_user_collections": [],
    "sponsorship": null,
    "topic_submissions": {},
    "user": {
      "id": "yBd2HKDGEJM",
      "updated_at": "2023-01-12T10:39:43Z",
      "username": "hayleymurrayphoto",
      "name": "Hayley Murray",
      "first_name": "Hayley",
      "last_name": "Murray",
      "twitter_username": "hayleycmurray",
      "portfolio_url": "http://www.hayleymurray.com",
      "bio": "Photographer. Designer.\r\nIG: @hayleymurrayphoto",
      "location": "Flint, MI",
      "links": {
        "self": "https://api.unsplash.com/users/hayleymurrayphoto",
        "html": "https://unsplash.com/@hayleymurrayphoto",
        "photos": "https://api.unsplash.com/users/hayleymurrayphoto/photos",
        "likes": "https://api.unsplash.com/users/hayleymurrayphoto/likes",
        "portfolio": "https://api.unsplash.com/users/hayleymurrayphoto/portfolio",
        "following": "https://api.unsplash.com/users/hayleymurrayphoto/following",
        "followers": "https://api.unsplash.com/users/hayleymurrayphoto/followers"
      },
      "profile_image": {
        "small": "https://images.unsplash.com/profile-1665671915231-c8cee9dfd13d?ixlib=rb-4.0.3&crop=faces&fit=crop&w=32&h=32",
        "medium": "https://images.unsplash.com/profile-1665671915231-c8cee9dfd13d?ixlib=rb-4.0.3&crop=faces&fit=crop&w=64&h=64",
        "large": "https://images.unsplash.com/profile-1665671915231-c8cee9dfd13d?ixlib=rb-4.0.3&crop=faces&fit=crop&w=128&h=128"
      },
      "instagram_username": "hayleymurrayphoto",
      "total_collections": 1,
      "total_likes": 3,
      "total_photos": 109,
      "accepted_tos": true,
      "for_hire": true,
      "social": {
        "instagram_username": "hayleymurrayphoto",
        "portfolio_url": "http://www.hayleymurray.com",
        "twitter_username": "hayleycmurray",
        "paypal_email": null
      }
    }
  },
  {
    "id": "gvvVftHG8ds",
    "created_at": "2023-01-08T11:13:06Z",
    "updated_at": "2023-01-12T10:41:03Z",
    "promoted_at": "2023-01-12T10:37:59Z",
    "width": 7378,
    "height": 5191,
    "color": "#c0c0c0",
    "blur_hash": "LcG[_]%MNHM{_NxuaxRjNLxaofof",
    "description": null,
    "alt_description": "a yellow sports car driving down the road",
    "urls": {
      "raw": "https://images.unsplash.com/photo-1673176313956-0ad653dea3f2?ixid=MnwzODY1NDR8MHwxfGFsbHwxM3x8fHx8fDJ8fDE2NzM1MjI2NjI&ixlib=rb-4.0.3",
      "full": "https://images.unsplash.com/photo-1673176313956-0ad653dea3f2?crop=entropy&cs=tinysrgb&fm=jpg&ixid=MnwzODY1NDR8MHwxfGFsbHwxM3x8fHx8fDJ8fDE2NzM1MjI2NjI&ixlib=rb-4.0.3&q=80",
      "regular": "https://images.unsplash.com/photo-1673176313956-0ad653dea3f2?crop=entropy&cs=tinysrgb&fit=max&fm=jpg&ixid=MnwzODY1NDR8MHwxfGFsbHwxM3x8fHx8fDJ8fDE2NzM1MjI2NjI&ixlib=rb-4.0.3&q=80&w=1080",
      "small": "https://images.unsplash.com/photo-1673176313956-0ad653dea3f2?crop=entropy&cs=tinysrgb&fit=max&fm=jpg&ixid=MnwzODY1NDR8MHwxfGFsbHwxM3x8fHx8fDJ8fDE2NzM1MjI2NjI&ixlib=rb-4.0.3&q=80&w=400",
      "thumb": "https://images.unsplash.com/photo-1673176313956-0ad653dea3f2?crop=entropy&cs=tinysrgb&fit=max&fm=jpg&ixid=MnwzODY1NDR8MHwxfGFsbHwxM3x8fHx8fDJ8fDE2NzM1MjI2NjI&ixlib=rb-4.0.3&q=80&w=200",
      "small_s3": "https://s3.us-west-2.amazonaws.com/images.unsplash.com/small/photo-1673176313956-0ad653dea3f2"
    },
    "links": {
      "self": "https://api.unsplash.com/photos/gvvVftHG8ds",
      "html": "https://unsplash.com/photos/gvvVftHG8ds",
      "download": "https://unsplash.com/photos/gvvVftHG8ds/download?ixid=MnwzODY1NDR8MHwxfGFsbHwxM3x8fHx8fDJ8fDE2NzM1MjI2NjI",
      "download_location": "https://api.unsplash.com/photos/gvvVftHG8ds/download?ixid=MnwzODY1NDR8MHwxfGFsbHwxM3x8fHx8fDJ8fDE2NzM1MjI2NjI"
    },
    "likes": 2,
    "liked_by_user": false,
    "current_user_collections": [],
    "sponsorship": null,
    "topic_submissions": {},
    "user": {
      "id": "1is5Uy1tt-4",
      "updated_at": "2023-01-12T10:38:47Z",
      "username": "carsbytim",
      "name": "Tim Krauss",
      "first_name": "Tim",
      "last_name": "Krauss",
      "twitter_username": null,
      "portfolio_url": null,
      "bio": null,
      "location": null,
      "links": {
        "self": "https://api.unsplash.com/users/carsbytim",
        "html": "https://unsplash.com/ja/@carsbytim",
        "photos": "https://api.unsplash.com/users/carsbytim/photos",
        "likes": "https://api.unsplash.com/users/carsbytim/likes",
        "portfolio": "https://api.unsplash.com/users/carsbytim/portfolio",
        "following": "https://api.unsplash.com/users/carsbytim/following",
        "followers": "https://api.unsplash.com/users/carsbytim/followers"
      },
      "profile_image": {
        "small": "https://images.unsplash.com/profile-fb-1519557293-0729a36ad324.jpg?ixlib=rb-4.0.3&crop=faces&fit=crop&w=32&h=32",
        "medium": "https://images.unsplash.com/profile-fb-1519557293-0729a36ad324.jpg?ixlib=rb-4.0.3&crop=faces&fit=crop&w=64&h=64",
        "large": "https://images.unsplash.com/profile-fb-1519557293-0729a36ad324.jpg?ixlib=rb-4.0.3&crop=faces&fit=crop&w=128&h=128"
      },
      "instagram_username": null,
      "total_collections": 0,
      "total_likes": 1,
      "total_photos": 8,
      "accepted_tos": true,
      "for_hire": false,
      "social": {
        "instagram_username": null,
        "portfolio_url": null,
        "twitter_username": null,
        "paypal_email": null
      }
    }
  },
  {
    "id": "13MovIElsDY",
    "created_at": "2023-01-11T21:02:19Z",
    "updated_at": "2023-01-12T10:40:57Z",
    "promoted_at": "2023-01-12T10:37:54Z",
    "width": 4480,
    "height": 6720,
    "color": "#f3c059",
    "blur_hash": "LGPX20JAxY5TVts9NINb}-$~xZ^N",
    "description": null,
    "alt_description": "a close up of a pasta dish with mushrooms and spinach",
    "urls": {
      "raw": "https://images.unsplash.com/photo-1673470743263-bf1a61b7f12e?ixid=MnwzODY1NDR8MHwxfGFsbHwxNHx8fHx8fDJ8fDE2NzM1MjI2NjI&ixlib=rb-4.0.3",
      "full": "https://images.unsplash.com/photo-1673470743263-bf1a61b7f12e?crop=entropy&cs=tinysrgb&fm=jpg&ixid=MnwzODY1NDR8MHwxfGFsbHwxNHx8fHx8fDJ8fDE2NzM1MjI2NjI&ixlib=rb-4.0.3&q=80",
      "regular": "https://images.unsplash.com/photo-1673470743263-bf1a61b7f12e?crop=entropy&cs=tinysrgb&fit=max&fm=jpg&ixid=MnwzODY1NDR8MHwxfGFsbHwxNHx8fHx8fDJ8fDE2NzM1MjI2NjI&ixlib=rb-4.0.3&q=80&w=1080",
      "small": "https://images.unsplash.com/photo-1673470743263-bf1a61b7f12e?crop=entropy&cs=tinysrgb&fit=max&fm=jpg&ixid=MnwzODY1NDR8MHwxfGFsbHwxNHx8fHx8fDJ8fDE2NzM1MjI2NjI&ixlib=rb-4.0.3&q=80&w=400",
      "thumb": "https://images.unsplash.com/photo-1673470743263-bf1a61b7f12e?crop=entropy&cs=tinysrgb&fit=max&fm=jpg&ixid=MnwzODY1NDR8MHwxfGFsbHwxNHx8fHx8fDJ8fDE2NzM1MjI2NjI&ixlib=rb-4.0.3&q=80&w=200",
      "small_s3": "https://s3.us-west-2.amazonaws.com/images.unsplash.com/small/photo-1673470743263-bf1a61b7f12e"
    },
    "links": {
      "self": "https://api.unsplash.com/photos/13MovIElsDY",
      "html": "https://unsplash.com/photos/13MovIElsDY",
      "download": "https://unsplash.com/photos/13MovIElsDY/download?ixid=MnwzODY1NDR8MHwxfGFsbHwxNHx8fHx8fDJ8fDE2NzM1MjI2NjI",
      "download_location": "https://api.unsplash.com/photos/13MovIElsDY/download?ixid=MnwzODY1NDR8MHwxfGFsbHwxNHx8fHx8fDJ8fDE2NzM1MjI2NjI"
    },
    "likes": 2,
    "liked_by_user": false,
    "current_user_collections": [],
    "sponsorship": null,
    "topic_submissions": {},
    "user": {
      "id": "AJaSdqYUTig",
      "updated_at": "2023-01-12T10:37:56Z",
      "username": "nixcreative",
      "name": "Tyler Nix",
      "first_name": "Tyler",
      "last_name": "Nix",
      "twitter_username": null,
      "portfolio_url": "http://thenixcreative.com",
      "bio": "Founder and Creative Specialist of Nix Creative. Building brands and creating dope a** content.",
      "location": "Los Angeles, CA",
      "links": {
        "self": "https://api.unsplash.com/users/nixcreative",
        "html": "https://unsplash.com/fr/@nixcreative",
        "photos": "https://api.unsplash.com/users/nixcreative/photos",
        "likes": "https://api.unsplash.com/users/nixcreative/likes",
        "portfolio": "https://api.unsplash.com/users/nixcreative/portfolio",
        "following": "https://api.unsplash.com/users/nixcreative/following",
        "followers": "https://api.unsplash.com/users/nixcreative/followers"
      },
      "profile_image": {
        "small": "https://images.unsplash.com/profile-1646754141355-e7af15c7bb5cimage?ixlib=rb-4.0.3&crop=faces&fit=crop&w=32&h=32",
        "medium": "https://images.unsplash.com/profile-1646754141355-e7af15c7bb5cimage?ixlib=rb-4.0.3&crop=faces&fit=crop&w=64&h=64",
        "large": "https://images.unsplash.com/profile-1646754141355-e7af15c7bb5cimage?ixlib=rb-4.0.3&crop=faces&fit=crop&w=128&h=128"
      },
      "instagram_username": "thenixcreative",
      "total_collections": 8,
      "total_likes": 736,
      "total_photos": 800,
      "accepted_tos": true,
      "for_hire": true,
      "social": {
        "instagram_username": "thenixcreative",
        "portfolio_url": "http://thenixcreative.com",
        "twitter_username": null,
        "paypal_email": null
      }
    }
  },
  {
    "id": "9pe2UPqAfo8",
    "created_at": "2023-01-10T15:46:48Z",
    "updated_at": "2023-01-12T10:40:44Z",
    "promoted_at": "2023-01-12T10:37:35Z",
    "width": 3892,
    "height": 5838,
    "color": "#0c2626",
    "blur_hash": "LvIN%4-;ogV@~VxuR-M|j]ozfkjZ",
    "description": null,
    "alt_description": "a person riding a bike on a city street",
    "urls": {
      "raw": "https://images.unsplash.com/photo-1673364433064-b1dd2a0a4890?ixid=MnwzODY1NDR8MHwxfGFsbHwxNXx8fHx8fDJ8fDE2NzM1MjI2NjI&ixlib=rb-4.0.3",
      "full": "https://images.unsplash.com/photo-1673364433064-b1dd2a0a4890?crop=entropy&cs=tinysrgb&fm=jpg&ixid=MnwzODY1NDR8MHwxfGFsbHwxNXx8fHx8fDJ8fDE2NzM1MjI2NjI&ixlib=rb-4.0.3&q=80",
      "regular": "https://images.unsplash.com/photo-1673364433064-b1dd2a0a4890?crop=entropy&cs=tinysrgb&fit=max&fm=jpg&ixid=MnwzODY1NDR8MHwxfGFsbHwxNXx8fHx8fDJ8fDE2NzM1MjI2NjI&ixlib=rb-4.0.3&q=80&w=1080",
      "small": "https://images.unsplash.com/photo-1673364433064-b1dd2a0a4890?crop=entropy&cs=tinysrgb&fit=max&fm=jpg&ixid=MnwzODY1NDR8MHwxfGFsbHwxNXx8fHx8fDJ8fDE2NzM1MjI2NjI&ixlib=rb-4.0.3&q=80&w=400",
      "thumb": "https://images.unsplash.com/photo-1673364433064-b1dd2a0a4890?crop=entropy&cs=tinysrgb&fit=max&fm=jpg&ixid=MnwzODY1NDR8MHwxfGFsbHwxNXx8fHx8fDJ8fDE2NzM1MjI2NjI&ixlib=rb-4.0.3&q=80&w=200",
      "small_s3": "https://s3.us-west-2.amazonaws.com/images.unsplash.com/small/photo-1673364433064-b1dd2a0a4890"
    },
    "links": {
      "self": "https://api.unsplash.com/photos/9pe2UPqAfo8",
      "html": "https://unsplash.com/photos/9pe2UPqAfo8",
      "download": "https://unsplash.com/photos/9pe2UPqAfo8/download?ixid=MnwzODY1NDR8MHwxfGFsbHwxNXx8fHx8fDJ8fDE2NzM1MjI2NjI",
      "download_location": "https://api.unsplash.com/photos/9pe2UPqAfo8/download?ixid=MnwzODY1NDR8MHwxfGFsbHwxNXx8fHx8fDJ8fDE2NzM1MjI2NjI"
    },
    "likes": 1,
    "liked_by_user": false,
    "current_user_collections": [],
    "sponsorship": null,
    "topic_submissions": {},
    "user": {
      "id": "CZevM0BbJv0",
      "updated_at": "2023-01-12T10:45:17Z",
      "username": "bastien_nvs",
      "name": "Bastien Nvs",
      "first_name": "Bastien",
      "last_name": "Nvs",
      "twitter_username": null,
      "portfolio_url": "https://bastienneves.wixsite.com/bastienneves",
      "bio": "Bastien\r\n📷 | PHOTOGRAPHER & FILMMAKER 📍 | Lyon, Paris  | linktr.ee/Bastiennvs INSTAGRAM : @bastien_nvs",
      "location": "Paris",
      "links": {
        "self": "https://api.unsplash.com/users/bastien_nvs",
        "html": "https://unsplash.com/@bastien_nvs",
        "photos": "https://api.unsplash.com/users/bastien_nvs/photos",
        "likes": "https://api.unsplash.com/users/bastien_nvs/likes",
        "portfolio": "https://api.unsplash.com/users/bastien_nvs/portfolio",
        "following": "https://api.unsplash.com/users/bastien_nvs/following",
        "followers": "https://api.unsplash.com/users/bastien_nvs/followers"
      },
      "profile_image": {
        "small": "https://images.unsplash.com/profile-1648894866827-e5137814b51fimage?ixlib=rb-4.0.3&crop=faces&fit=crop&w=32&h=32",
        "medium": "https://images.unsplash.com/profile-1648894866827-e5137814b51fimage?ixlib=rb-4.0.3&crop=faces&fit=crop&w=64&h=64",
        "large": "https://images.unsplash.com/profile-1648894866827-e5137814b51fimage?ixlib=rb-4.0.3&crop=faces&fit=crop&w=128&h=128"
      },
      "instagram_username": "bastien_nvs",
      "total_collections": 2,
      "total_likes": 35,
      "total_photos": 479,
      "accepted_tos": true,
      "for_hire": true,
      "social": {
        "instagram_username": "bastien_nvs",
        "portfolio_url": "https://bastienneves.wixsite.com/bastienneves",
        "twitter_username": null,
        "paypal_email": null
      }
    }
  },
  {
    "id": "oo_xunM0CcE",
    "created_at": "2022-12-22T16:34:39Z",
    "updated_at": "2023-01-12T06:33:17Z",
    "promoted_at": null,
    "width": 8368,
    "height": 5584,
    "color": "#a6a6a6",
    "blur_hash": "LCGR^+Hqe7~W_3NI5SE1McMy_3IU",
    "description": null,
    "alt_description": "a laptop computer sitting on top of a table",
    "urls": {
      "raw": "https://images.unsplash.com/photo-1671726805768-575f88de945a?ixid=MnwzODY1NDR8MXwxfGFsbHwxNnx8fHx8fDJ8fDE2NzM1MjI2NjI&ixlib=rb-4.0.3",
      "full": "https://images.unsplash.com/photo-1671726805768-575f88de945a?crop=entropy&cs=tinysrgb&fm=jpg&ixid=MnwzODY1NDR8MXwxfGFsbHwxNnx8fHx8fDJ8fDE2NzM1MjI2NjI&ixlib=rb-4.0.3&q=80",
      "regular": "https://images.unsplash.com/photo-1671726805768-575f88de945a?crop=entropy&cs=tinysrgb&fit=max&fm=jpg&ixid=MnwzODY1NDR8MXwxfGFsbHwxNnx8fHx8fDJ8fDE2NzM1MjI2NjI&ixlib=rb-4.0.3&q=80&w=1080",
      "small": "https://images.unsplash.com/photo-1671726805768-575f88de945a?crop=entropy&cs=tinysrgb&fit=max&fm=jpg&ixid=MnwzODY1NDR8MXwxfGFsbHwxNnx8fHx8fDJ8fDE2NzM1MjI2NjI&ixlib=rb-4.0.3&q=80&w=400",
      "thumb": "https://images.unsplash.com/photo-1671726805768-575f88de945a?crop=entropy&cs=tinysrgb&fit=max&fm=jpg&ixid=MnwzODY1NDR8MXwxfGFsbHwxNnx8fHx8fDJ8fDE2NzM1MjI2NjI&ixlib=rb-4.0.3&q=80&w=200",
      "small_s3": "https://s3.us-west-2.amazonaws.com/images.unsplash.com/small/photo-1671726805768-575f88de945a"
    },
    "links": {
      "self": "https://api.unsplash.com/photos/oo_xunM0CcE",
      "html": "https://unsplash.com/photos/oo_xunM0CcE",
      "download": "https://unsplash.com/photos/oo_xunM0CcE/download?ixid=MnwzODY1NDR8MXwxfGFsbHwxNnx8fHx8fDJ8fDE2NzM1MjI2NjI",
      "download_location": "https://api.unsplash.com/photos/oo_xunM0CcE/download?ixid=MnwzODY1NDR8MXwxfGFsbHwxNnx8fHx8fDJ8fDE2NzM1MjI2NjI"
    },
    "likes": 21,
    "liked_by_user": false,
    "current_user_collections": [],
    "sponsorship": {
      "impression_urls": [
        "https://secure.insightexpressai.com/adServer/adServerESI.aspx?script=false&bannerID=11051548&rnd=[timestamp]&redir=https://secure.insightexpressai.com/adserver/1pixel.gif"
      ],
      "tagline": "Helps you achieve more in less time",
      "tagline_url": "https://www.microsoft.com/en-us/microsoft-365?ocid=UnsplashFY23_soc_pmc_m365_",
      "sponsor": {
        "id": "VKlg9Ffk2GE",
        "updated_at": "2023-01-12T08:02:19Z",
        "username": "microsoft365",
        "name": "Microsoft 365",
        "first_name": "Microsoft",
        "last_name": "365",
        "twitter_username": "Microsoft365",
        "portfolio_url": "https://www.microsoft.com/en-us/microsoft-365",
        "bio": "Microsoft 365 is designed to help you achieve more across work and life with innovative Office apps, intelligent cloud services, and world-class security.",
        "location": null,
        "links": {
          "self": "https://api.unsplash.com/users/microsoft365",
          "html": "https://unsplash.com/@microsoft365",
          "photos": "https://api.unsplash.com/users/microsoft365/photos",
          "likes": "https://api.unsplash.com/users/microsoft365/likes",
          "portfolio": "https://api.unsplash.com/users/microsoft365/portfolio",
          "following": "https://api.unsplash.com/users/microsoft365/following",
          "followers": "https://api.unsplash.com/users/microsoft365/followers"
        },
        "profile_image": {
          "small": "https://images.unsplash.com/profile-1605642019416-f1f5d5d75bfbimage?ixlib=rb-4.0.3&crop=faces&fit=crop&w=32&h=32",
          "medium": "https://images.unsplash.com/profile-1605642019416-f1f5d5d75bfbimage?ixlib=rb-4.0.3&crop=faces&fit=crop&w=64&h=64",
          "large": "https://images.unsplash.com/profile-1605642019416-f1f5d5d75bfbimage?ixlib=rb-4.0.3&crop=faces&fit=crop&w=128&h=128"
        },
        "instagram_username": null,
        "total_collections": 0,
        "total_likes": 0,
        "total_photos": 27,
        "accepted_tos": true,
        "for_hire": false,
        "social": {
          "instagram_username": null,
          "portfolio_url": "https://www.microsoft.com/en-us/microsoft-365",
          "twitter_username": "Microsoft365",
          "paypal_email": null
        }
      }
    },
    "topic_submissions": {},
    "user": {
      "id": "VKlg9Ffk2GE",
      "updated_at": "2023-01-12T08:02:19Z",
      "username": "microsoft365",
      "name": "Microsoft 365",
      "first_name": "Microsoft",
      "last_name": "365",
      "twitter_username": "Microsoft365",
      "portfolio_url": "https://www.microsoft.com/en-us/microsoft-365",
      "bio": "Microsoft 365 is designed to help you achieve more across work and life with innovative Office apps, intelligent cloud services, and world-class security.",
      "location": null,
      "links": {
        "self": "https://api.unsplash.com/users/microsoft365",
        "html": "https://unsplash.com/@microsoft365",
        "photos": "https://api.unsplash.com/users/microsoft365/photos",
        "likes": "https://api.unsplash.com/users/microsoft365/likes",
        "portfolio": "https://api.unsplash.com/users/microsoft365/portfolio",
        "following": "https://api.unsplash.com/users/microsoft365/following",
        "followers": "https://api.unsplash.com/users/microsoft365/followers"
      },
      "profile_image": {
        "small": "https://images.unsplash.com/profile-1605642019416-f1f5d5d75bfbimage?ixlib=rb-4.0.3&crop=faces&fit=crop&w=32&h=32",
        "medium": "https://images.unsplash.com/profile-1605642019416-f1f5d5d75bfbimage?ixlib=rb-4.0.3&crop=faces&fit=crop&w=64&h=64",
        "large": "https://images.unsplash.com/profile-1605642019416-f1f5d5d75bfbimage?ixlib=rb-4.0.3&crop=faces&fit=crop&w=128&h=128"
      },
      "instagram_username": null,
      "total_collections": 0,
      "total_likes": 0,
      "total_photos": 27,
      "accepted_tos": true,
      "for_hire": false,
      "social": {
        "instagram_username": null,
        "portfolio_url": "https://www.microsoft.com/en-us/microsoft-365",
        "twitter_username": "Microsoft365",
        "paypal_email": null
      }
    }
  },
  {
    "id": "8Me9BDLYURE",
    "created_at": "2023-01-09T08:32:17Z",
    "updated_at": "2023-01-12T10:39:22Z",
    "promoted_at": "2023-01-12T10:36:15Z",
    "width": 3000,
    "height": 3000,
    "color": "#a6a6a6",
    "blur_hash": "LQDx8,=xRPe.0|nOsoRjrXR*ofnj",
    "description": null,
    "alt_description": "an aerial view of a boat on a beach",
    "urls": {
      "raw": "https://images.unsplash.com/photo-1673253082952-4ba1b404e5ee?ixid=MnwzODY1NDR8MHwxfGFsbHwxN3x8fHx8fDJ8fDE2NzM1MjI2NjI&ixlib=rb-4.0.3",
      "full": "https://images.unsplash.com/photo-1673253082952-4ba1b404e5ee?crop=entropy&cs=tinysrgb&fm=jpg&ixid=MnwzODY1NDR8MHwxfGFsbHwxN3x8fHx8fDJ8fDE2NzM1MjI2NjI&ixlib=rb-4.0.3&q=80",
      "regular": "https://images.unsplash.com/photo-1673253082952-4ba1b404e5ee?crop=entropy&cs=tinysrgb&fit=max&fm=jpg&ixid=MnwzODY1NDR8MHwxfGFsbHwxN3x8fHx8fDJ8fDE2NzM1MjI2NjI&ixlib=rb-4.0.3&q=80&w=1080",
      "small": "https://images.unsplash.com/photo-1673253082952-4ba1b404e5ee?crop=entropy&cs=tinysrgb&fit=max&fm=jpg&ixid=MnwzODY1NDR8MHwxfGFsbHwxN3x8fHx8fDJ8fDE2NzM1MjI2NjI&ixlib=rb-4.0.3&q=80&w=400",
      "thumb": "https://images.unsplash.com/photo-1673253082952-4ba1b404e5ee?crop=entropy&cs=tinysrgb&fit=max&fm=jpg&ixid=MnwzODY1NDR8MHwxfGFsbHwxN3x8fHx8fDJ8fDE2NzM1MjI2NjI&ixlib=rb-4.0.3&q=80&w=200",
      "small_s3": "https://s3.us-west-2.amazonaws.com/images.unsplash.com/small/photo-1673253082952-4ba1b404e5ee"
    },
    "links": {
      "self": "https://api.unsplash.com/photos/8Me9BDLYURE",
      "html": "https://unsplash.com/photos/8Me9BDLYURE",
      "download": "https://unsplash.com/photos/8Me9BDLYURE/download?ixid=MnwzODY1NDR8MHwxfGFsbHwxN3x8fHx8fDJ8fDE2NzM1MjI2NjI",
      "download_location": "https://api.unsplash.com/photos/8Me9BDLYURE/download?ixid=MnwzODY1NDR8MHwxfGFsbHwxN3x8fHx8fDJ8fDE2NzM1MjI2NjI"
    },
    "likes": 2,
    "liked_by_user": false,
    "current_user_collections": [],
    "sponsorship": null,
    "topic_submissions": {},
    "user": {
      "id": "YHWXggnQnHY",
      "updated_at": "2023-01-12T10:36:15Z",
      "username": "ahmedd_saalim",
      "name": "Ahmed Saalim Hussain",
      "first_name": "Ahmed Saalim",
      "last_name": "Hussain",
      "twitter_username": null,
      "portfolio_url": null,
      "bio": null,
      "location": "Maldives",
      "links": {
        "self": "https://api.unsplash.com/users/ahmedd_saalim",
        "html": "https://unsplash.com/@ahmedd_saalim",
        "photos": "https://api.unsplash.com/users/ahmedd_saalim/photos",
        "likes": "https://api.unsplash.com/users/ahmedd_saalim/likes",
        "portfolio": "https://api.unsplash.com/users/ahmedd_saalim/portfolio",
        "following": "https://api.unsplash.com/users/ahmedd_saalim/following",
        "followers": "https://api.unsplash.com/users/ahmedd_saalim/followers"
      },
      "profile_image": {
        "small": "https://images.unsplash.com/profile-1673195084236-ccefb0e1bb75image?ixlib=rb-4.0.3&crop=faces&fit=crop&w=32&h=32",
        "medium": "https://images.unsplash.com/profile-1673195084236-ccefb0e1bb75image?ixlib=rb-4.0.3&crop=faces&fit=crop&w=64&h=64",
        "large": "https://images.unsplash.com/profile-1673195084236-ccefb0e1bb75image?ixlib=rb-4.0.3&crop=faces&fit=crop&w=128&h=128"
      },
      "instagram_username": "ahmedd_saalim",
      "total_collections": 0,
      "total_likes": 5,
      "total_photos": 16,
      "accepted_tos": true,
      "for_hire": false,
      "social": {
        "instagram_username": "ahmedd_saalim",
        "portfolio_url": null,
        "twitter_username": null,
        "paypal_email": null
      }
    }
  },
  {
    "id": "MPG70uNPw1c",
    "created_at": "2023-01-11T22:23:28Z",
    "updated_at": "2023-01-12T11:11:04Z",
    "promoted_at": "2023-01-12T10:34:27Z",
    "width": 2158,
    "height": 3236,
    "color": "#d9d9f3",
    "blur_hash": "LjJt=0Ri9tn$~Wayjbj[^+t7X9fl",
    "description": null,
    "alt_description": "a body of water with a dock in the middle of it",
    "urls": {
      "raw": "https://images.unsplash.com/photo-1673475681199-7574a292b688?ixid=MnwzODY1NDR8MHwxfGFsbHwxOHx8fHx8fDJ8fDE2NzM1MjI2NjI&ixlib=rb-4.0.3",
      "full": "https://images.unsplash.com/photo-1673475681199-7574a292b688?crop=entropy&cs=tinysrgb&fm=jpg&ixid=MnwzODY1NDR8MHwxfGFsbHwxOHx8fHx8fDJ8fDE2NzM1MjI2NjI&ixlib=rb-4.0.3&q=80",
      "regular": "https://images.unsplash.com/photo-1673475681199-7574a292b688?crop=entropy&cs=tinysrgb&fit=max&fm=jpg&ixid=MnwzODY1NDR8MHwxfGFsbHwxOHx8fHx8fDJ8fDE2NzM1MjI2NjI&ixlib=rb-4.0.3&q=80&w=1080",
      "small": "https://images.unsplash.com/photo-1673475681199-7574a292b688?crop=entropy&cs=tinysrgb&fit=max&fm=jpg&ixid=MnwzODY1NDR8MHwxfGFsbHwxOHx8fHx8fDJ8fDE2NzM1MjI2NjI&ixlib=rb-4.0.3&q=80&w=400",
      "thumb": "https://images.unsplash.com/photo-1673475681199-7574a292b688?crop=entropy&cs=tinysrgb&fit=max&fm=jpg&ixid=MnwzODY1NDR8MHwxfGFsbHwxOHx8fHx8fDJ8fDE2NzM1MjI2NjI&ixlib=rb-4.0.3&q=80&w=200",
      "small_s3": "https://s3.us-west-2.amazonaws.com/images.unsplash.com/small/photo-1673475681199-7574a292b688"
    },
    "links": {
      "self": "https://api.unsplash.com/photos/MPG70uNPw1c",
      "html": "https://unsplash.com/photos/MPG70uNPw1c",
      "download": "https://unsplash.com/photos/MPG70uNPw1c/download?ixid=MnwzODY1NDR8MHwxfGFsbHwxOHx8fHx8fDJ8fDE2NzM1MjI2NjI",
      "download_location": "https://api.unsplash.com/photos/MPG70uNPw1c/download?ixid=MnwzODY1NDR8MHwxfGFsbHwxOHx8fHx8fDJ8fDE2NzM1MjI2NjI"
    },
    "likes": 6,
    "liked_by_user": false,
    "current_user_collections": [],
    "sponsorship": null,
    "topic_submissions": {},
    "user": {
      "id": "MIBmm8_pVqU",
      "updated_at": "2023-01-12T10:38:46Z",
      "username": "neganova",
      "name": "Valeriia Neganova",
      "first_name": "Valeriia",
      "last_name": "Neganova",
      "twitter_username": null,
      "portfolio_url": null,
      "bio": null,
      "location": "Florida, USA",
      "links": {
        "self": "https://api.unsplash.com/users/neganova",
        "html": "https://unsplash.com/@neganova",
        "photos": "https://api.unsplash.com/users/neganova/photos",
        "likes": "https://api.unsplash.com/users/neganova/likes",
        "portfolio": "https://api.unsplash.com/users/neganova/portfolio",
        "following": "https://api.unsplash.com/users/neganova/following",
        "followers": "https://api.unsplash.com/users/neganova/followers"
      },
      "profile_image": {
        "small": "https://images.unsplash.com/profile-1652113863826-625b75bd747dimage?ixlib=rb-4.0.3&crop=faces&fit=crop&w=32&h=32",
        "medium": "https://images.unsplash.com/profile-1652113863826-625b75bd747dimage?ixlib=rb-4.0.3&crop=faces&fit=crop&w=64&h=64",
        "large": "https://images.unsplash.com/profile-1652113863826-625b75bd747dimage?ixlib=rb-4.0.3&crop=faces&fit=crop&w=128&h=128"
      },
      "instagram_username": "neganova.cam",
      "total_collections": 0,
      "total_likes": 0,
      "total_photos": 120,
      "accepted_tos": true,
      "for_hire": true,
      "social": {
        "instagram_username": "neganova.cam",
        "portfolio_url": null,
        "twitter_username": null,
        "paypal_email": null
      }
    }
  },
  {
    "id": "mKG3nYgEVIY",
    "created_at": "2023-01-11T23:32:19Z",
    "updated_at": "2023-01-12T11:03:45Z",
    "promoted_at": "2023-01-12T10:34:14Z",
    "width": 4000,
    "height": 5000,
    "color": "#f3c0c0",
    "blur_hash": "LZPrhIM2PVa2R@V?k8X8{yo|aJkC",
    "description": null,
    "alt_description": "a blurry image of cubes on a pink and blue background",
    "urls": {
      "raw": "https://images.unsplash.com/photo-1673479590411-853c4c035091?ixid=MnwzODY1NDR8MHwxfGFsbHwxOXx8fHx8fDJ8fDE2NzM1MjI2NjI&ixlib=rb-4.0.3",
      "full": "https://images.unsplash.com/photo-1673479590411-853c4c035091?crop=entropy&cs=tinysrgb&fm=jpg&ixid=MnwzODY1NDR8MHwxfGFsbHwxOXx8fHx8fDJ8fDE2NzM1MjI2NjI&ixlib=rb-4.0.3&q=80",
      "regular": "https://images.unsplash.com/photo-1673479590411-853c4c035091?crop=entropy&cs=tinysrgb&fit=max&fm=jpg&ixid=MnwzODY1NDR8MHwxfGFsbHwxOXx8fHx8fDJ8fDE2NzM1MjI2NjI&ixlib=rb-4.0.3&q=80&w=1080",
      "small": "https://images.unsplash.com/photo-1673479590411-853c4c035091?crop=entropy&cs=tinysrgb&fit=max&fm=jpg&ixid=MnwzODY1NDR8MHwxfGFsbHwxOXx8fHx8fDJ8fDE2NzM1MjI2NjI&ixlib=rb-4.0.3&q=80&w=400",
      "thumb": "https://images.unsplash.com/photo-1673479590411-853c4c035091?crop=entropy&cs=tinysrgb&fit=max&fm=jpg&ixid=MnwzODY1NDR8MHwxfGFsbHwxOXx8fHx8fDJ8fDE2NzM1MjI2NjI&ixlib=rb-4.0.3&q=80&w=200",
      "small_s3": "https://s3.us-west-2.amazonaws.com/images.unsplash.com/small/photo-1673479590411-853c4c035091"
    },
    "links": {
      "self": "https://api.unsplash.com/photos/mKG3nYgEVIY",
      "html": "https://unsplash.com/photos/mKG3nYgEVIY",
      "download": "https://unsplash.com/photos/mKG3nYgEVIY/download?ixid=MnwzODY1NDR8MHwxfGFsbHwxOXx8fHx8fDJ8fDE2NzM1MjI2NjI",
      "download_location": "https://api.unsplash.com/photos/mKG3nYgEVIY/download?ixid=MnwzODY1NDR8MHwxfGFsbHwxOXx8fHx8fDJ8fDE2NzM1MjI2NjI"
    },
    "likes": 3,
    "liked_by_user": false,
    "current_user_collections": [],
    "sponsorship": null,
    "topic_submissions": {
      "3d-renders": {
        "status": "unevaluated"
      }
    },
    "user": {
      "id": "wdrZcuVyaXg",
      "updated_at": "2023-01-12T10:38:46Z",
      "username": "jdiegoph",
      "name": "Diego PH",
      "first_name": "Diego",
      "last_name": "PH",
      "twitter_username": "j_diegoph",
      "portfolio_url": "http://www.instagram.com/j.diegoph/",
      "bio": "Digital Artist and Photograper //\r\nInstagram: @j.diegoph",
      "location": "Toluca, México. ",
      "links": {
        "self": "https://api.unsplash.com/users/jdiegoph",
        "html": "https://unsplash.com/@jdiegoph",
        "photos": "https://api.unsplash.com/users/jdiegoph/photos",
        "likes": "https://api.unsplash.com/users/jdiegoph/likes",
        "portfolio": "https://api.unsplash.com/users/jdiegoph/portfolio",
        "following": "https://api.unsplash.com/users/jdiegoph/following",
        "followers": "https://api.unsplash.com/users/jdiegoph/followers"
      },
      "profile_image": {
        "small": "https://images.unsplash.com/profile-1553882437332-2aaadee4ff49?ixlib=rb-4.0.3&crop=faces&fit=crop&w=32&h=32",
        "medium": "https://images.unsplash.com/profile-1553882437332-2aaadee4ff49?ixlib=rb-4.0.3&crop=faces&fit=crop&w=64&h=64",
        "large": "https://images.unsplash.com/profile-1553882437332-2aaadee4ff49?ixlib=rb-4.0.3&crop=faces&fit=crop&w=128&h=128"
      },
      "instagram_username": "j.diegoph",
      "total_collections": 1,
      "total_likes": 4006,
      "total_photos": 62,
      "accepted_tos": true,
      "for_hire": false,
      "social": {
        "instagram_username": "j.diegoph",
        "portfolio_url": "http://www.instagram.com/j.diegoph/",
        "twitter_username": "j_diegoph",
        "paypal_email": null
      }
    }
  },
  {
    "id": "X341uDCs5NQ",
    "created_at": "2023-01-11T13:43:33Z",
    "updated_at": "2023-01-12T11:23:51Z",
    "promoted_at": "2023-01-12T10:34:01Z",
    "width": 3648,
    "height": 5472,
    "color": "#595959",
    "blur_hash": "L9EoDA4:0#D*0#-nWC9u5R^*s;j]",
    "description": null,
    "alt_description": "a table topped with a book and a cup of coffee",
    "urls": {
      "raw": "https://images.unsplash.com/photo-1673444581939-bd908db3bca6?ixid=MnwzODY1NDR8MHwxfGFsbHwyMHx8fHx8fDJ8fDE2NzM1MjI2NjI&ixlib=rb-4.0.3",
      "full": "https://images.unsplash.com/photo-1673444581939-bd908db3bca6?crop=entropy&cs=tinysrgb&fm=jpg&ixid=MnwzODY1NDR8MHwxfGFsbHwyMHx8fHx8fDJ8fDE2NzM1MjI2NjI&ixlib=rb-4.0.3&q=80",
      "regular": "https://images.unsplash.com/photo-1673444581939-bd908db3bca6?crop=entropy&cs=tinysrgb&fit=max&fm=jpg&ixid=MnwzODY1NDR8MHwxfGFsbHwyMHx8fHx8fDJ8fDE2NzM1MjI2NjI&ixlib=rb-4.0.3&q=80&w=1080",
      "small": "https://images.unsplash.com/photo-1673444581939-bd908db3bca6?crop=entropy&cs=tinysrgb&fit=max&fm=jpg&ixid=MnwzODY1NDR8MHwxfGFsbHwyMHx8fHx8fDJ8fDE2NzM1MjI2NjI&ixlib=rb-4.0.3&q=80&w=400",
      "thumb": "https://images.unsplash.com/photo-1673444581939-bd908db3bca6?crop=entropy&cs=tinysrgb&fit=max&fm=jpg&ixid=MnwzODY1NDR8MHwxfGFsbHwyMHx8fHx8fDJ8fDE2NzM1MjI2NjI&ixlib=rb-4.0.3&q=80&w=200",
      "small_s3": "https://s3.us-west-2.amazonaws.com/images.unsplash.com/small/photo-1673444581939-bd908db3bca6"
    },
    "links": {
      "self": "https://api.unsplash.com/photos/X341uDCs5NQ",
      "html": "https://unsplash.com/photos/X341uDCs5NQ",
      "download": "https://unsplash.com/photos/X341uDCs5NQ/download?ixid=MnwzODY1NDR8MHwxfGFsbHwyMHx8fHx8fDJ8fDE2NzM1MjI2NjI",
      "download_location": "https://api.unsplash.com/photos/X341uDCs5NQ/download?ixid=MnwzODY1NDR8MHwxfGFsbHwyMHx8fHx8fDJ8fDE2NzM1MjI2NjI"
    },
    "likes": 1,
    "liked_by_user": false,
    "current_user_collections": [],
    "sponsorship": null,
    "topic_submissions": {},
    "user": {
      "id": "3Xw25ZLdUf8",
      "updated_at": "2023-01-12T11:21:45Z",
      "username": "yanutkaa1",
      "name": "Yana Gorbunova",
      "first_name": "Yana",
      "last_name": "Gorbunova",
      "twitter_username": "Yanutkaa1",
      "portfolio_url": "https://www.instagram.com/yana_grb/",
      "bio": null,
      "location": "Ukraine",
      "links": {
        "self": "https://api.unsplash.com/users/yanutkaa1",
        "html": "https://unsplash.com/@yanutkaa1",
        "photos": "https://api.unsplash.com/users/yanutkaa1/photos",
        "likes": "https://api.unsplash.com/users/yanutkaa1/likes",
        "portfolio": "https://api.unsplash.com/users/yanutkaa1/portfolio",
        "following": "https://api.unsplash.com/users/yanutkaa1/following",
        "followers": "https://api.unsplash.com/users/yanutkaa1/followers"
      },
      "profile_image": {
        "small": "https://images.unsplash.com/profile-1607438865229-0f2826835e09image?ixlib=rb-4.0.3&crop=faces&fit=crop&w=32&h=32",
        "medium": "https://images.unsplash.com/profile-1607438865229-0f2826835e09image?ixlib=rb-4.0.3&crop=faces&fit=crop&w=64&h=64",
        "large": "https://images.unsplash.com/profile-1607438865229-0f2826835e09image?ixlib=rb-4.0.3&crop=faces&fit=crop&w=128&h=128"
      },
      "instagram_username": "yana_grb",
      "total_collections": 0,
      "total_likes": 36,
      "total_photos": 406,
      "accepted_tos": true,
      "for_hire": true,
      "social": {
        "instagram_username": "yana_grb",
        "portfolio_url": "https://www.instagram.com/yana_grb/",
        "twitter_username": "Yanutkaa1",
        "paypal_email": null
      }
    }
  }
]